[
    {
        "track": "pr",
        "id": 1185,
        "text": "就是在于万有皆神论本身的弱点。因为否认了神的位格，以致无法承认人是自由与永存不朽的。他们的主张无所依据，非独未经证实，且是一种无法证实的臆说。　",
        "hypothesis": "人是自由与永存不朽的。"
    },
    {
        "track": "pr",
        "id": 1186,
        "text": "科学家认为，湿地在维持生态平衡上所起的作用极为关键。",
        "hypothesis": "湿地在维持生态平衡上所起的作用极为关键。"
    },
    {
        "track": "pr",
        "id": 1187,
        "text": "守在监控室屏幕前的保安人员没有看见有一个人趁着深夜月色翻越围墙进入了厂区。",
        "hypothesis": "有一个人趁着深夜月色翻越围墙进入了厂区。"
    },
    {
        "track": "pr",
        "id": 1188,
        "text": "这份由联合国安理会全票通过的决议草案明确规定了停火时间表和监督机制，标志着长达十年的地区武装冲突迎来了具有法律约束力的和平曙光。",
        "hypothesis": "长达十年的地区武装冲突没有迎来具有法律约束力的和平曙光。"
    },
    {
        "track": "pr",
        "id": 1189,
        "text": "二十日的周报是根据政府的统计写的，同样未加考虑，未做调查，就认为工作都已经做好了。",
        "hypothesis": "工作都没有做好。"
    },
    {
        "track": "pr",
        "id": 1190,
        "text": "其实作为学生的我在专业领域内心一直不敢妄称是张老师的学生，很多时候因为自己不够努力进取甚至不敢直面老师。 ",
        "hypothesis": "我是张老师的学生。"
    },
    {
        "track": "pr",
        "id": 1191,
        "text": "有个三岁的孩子，在电视中看到公园里的“登月火箭”很好玩，第二天家中来了客人，孩子告诉客人昨天妈妈带他去坐“登月火箭”了，这是孩子往往把幻想与现实混淆，把自己的愿望当成真了，不能指责他撒谎。",
        "hypothesis": "孩子没有撒谎。"
    },
    {
        "track": "pr",
        "id": 1192,
        "text": "2001年九运会上，广东以69.5枚金牌遥遥领先，但广东却一直不敢称自已是体育强省，就因为广东在奥运会上夺得的金牌少得可怜。",
        "hypothesis": "广东是体育强省。"
    },
    {
        "track": "pr",
        "id": 1193,
        "text": "西北区修筑某桥梁，没有钻探，就认为石层很深，确定了设计标准。",
        "hypothesis": "石层很深。"
    },
    {
        "track": "pr",
        "id": 1194,
        "text": "邻居们纷纷嫌那家新开的餐厅装修太过奢华，完全失去了老街原有的朴实韵味。",
        "hypothesis": "那家新开的餐厅装修没有过分奢华。"
    },
    {
        "track": "pr",
        "id": 1195,
        "text": "那艘潜艇在海面上伪装自己是一艘发生故障的民用货轮，故意让烟囱冒出黑烟并放慢航速以迷惑远处的侦察机。",
        "hypothesis": "那艘潜艇是一艘发生故障的民用货轮。"
    },
    {
        "track": "pr",
        "id": 1196,
        "text": "她嫉妒经理的才华，并诽谤他通过贿赂评审委员会成员才拿到了这个价值千万的工程项目。",
        "hypothesis": "项目经理通过贿赂评审委员会成员才拿到了这个价值千万的工程项目。"
    },
    {
        "track": "pr",
        "id": 1197,
        "text": "难怪外单位有的人在参观之后，并没有感觉出层高降低了。",
        "hypothesis": "层高没有降低。"
    },
    {
        "track": "pr",
        "id": 1198,
        "text": "其实它并不是不动的，只因它位于地球北极的正上方，离天北极很近(一度左右)，我们用肉眼察觉不到它在小幅度旋转。",
        "hypothesis": "它在小幅度旋转。"
    },
    {
        "track": "pr",
        "id": 1199,
        "text": "我们愿意进行全面的和解，但这并不表示我们放弃了原有的理想。",
        "hypothesis": "我们放弃了原有的理想。"
    },
    {
        "track": "pr",
        "id": 1200,
        "text": "电子在石墨烯中运动几乎没有阻力，迁移速度极快，是世上已知的电阻率最小的材料。因为这一特点，石墨烯被期待可用来发展更薄、导电速度更快的新一代电子元件或晶体管。",
        "hypothesis": "石墨烯可用来发展更薄、导电速度更快的新一代电子元件或晶体管。"
    },
    {
        "track": "pr",
        "id": 1201,
        "text": "我不想伤害她，但是我容忍不了她继续在你身边。",
        "hypothesis": "她不在你身边。"
    },
    {
        "track": "pr",
        "id": 1202,
        "text": "他还说，自从第二次世界大战结束以来，在苏联已经有了许多变化，克里姆林的领袖们不想看到他们建立起来的一切被摧毁。",
        "hypothesis": "克里姆林的领袖们建立起来的一切没有被摧毁。"
    },
    {
        "track": "pr",
        "id": 1203,
        "text": "史良宣读了邵慈云的信，邵慈云要求追查罗隆基为什么污蔑她有特务嫌疑。",
        "hypothesis": "邵慈云有特务嫌疑。"
    },
    {
        "track": "pr",
        "id": 1204,
        "text": "这些高管在过去几个月内涉嫌利用内幕信息提前买卖股票。",
        "hypothesis": "（这些高管）在过去几个月内利用内幕信息提前买卖股票。"
    },
    {
        "track": "pr",
        "id": 1205,
        "text": "女人说，她曾经爱上一个有妇之夫。他已经有太太和孩子了，并且没有否认自己很爱太太。 ",
        "hypothesis": "他不很爱太太。"
    },
    {
        "track": "pr",
        "id": 1206,
        "text": "文帝原是一位明主，一笑了事，并不责备慎夫人擅自作主。连这天的一席酒，也吃得分外有兴。",
        "hypothesis": "慎夫人擅自作了主。"
    },
    {
        "track": "pr",
        "id": 1207,
        "text": "他周六走26km再睡一宿热炕啥事儿没有，周日爬长城走河滩连蹦带跳的啥事儿没有，还差点企图再走回那段十几公里盘山路。",
        "hypothesis": "他走回了那段十几公里盘山路。"
    },
    {
        "track": "pr",
        "id": 1208,
        "text": "解放后，当去年该厂遣散工人时，与工人发生争执，经仲裁后，资方竟认为自己胜利了，就趁机打击工会干部，企图挑拨工会与政府之间的关系。",
        "hypothesis": "资方没有胜利。"
    },
    {
        "track": "pr",
        "id": 1209,
        "text": "广汉县委委员从实践中体会到集中精力抓经济要按经济规律办事。",
        "hypothesis": "集中精力抓经济要按经济规律办事。"
    },
    {
        "track": "pr",
        "id": 1210,
        "text": "谈判专家没准备直接同意绑匪提出的苛刻要求。",
        "hypothesis": "谈判专家不会直接同意绑匪提出的苛刻要求。"
    },
    {
        "track": "pr",
        "id": 1211,
        "text": "我在事前绝不知道夏天义要请夏天智他们也来吃饭的。",
        "hypothesis": "夏天义没有请夏天智他们来吃饭。"
    },
    {
        "track": "pr",
        "id": 1212,
        "text": "他并不羡慕自己的哥哥可以继承那些权力和责任。",
        "hypothesis": "他的哥哥可以继承那些权力和责任。"
    },
    {
        "track": "pr",
        "id": 1213,
        "text": "这些关注的视线，进一步探知到中国经济的底气之足——迈向高质量发展的中国经济积聚着强劲韧性，焕发着生机活力。",
        "hypothesis": "中国经济的底气很足。"
    },
    {
        "track": "pr",
        "id": 1214,
        "text": "有些家长盲目地相信鼓励是唯一的方法，或是一味地严格要求。",
        "hypothesis": "鼓励不是唯一的方法。"
    },
    {
        "track": "pr",
        "id": 1215,
        "text": "长期以来，美联储的决策机制时常被抱怨定义模糊。事实上，美联储经常会陷入决策困境之中。",
        "hypothesis": "长期以来，美联储的决策机制定义不模糊。"
    },
    {
        "track": "pr",
        "id": 1216,
        "text": "尽管伪装得十分巧妙，经验丰富的老侦探还是瞬间认出混迹于宾客之中的嫌疑人就是三年前那场银行劫案的主谋。",
        "hypothesis": "混迹于宾客之中的嫌疑人不是三年前那场银行劫案的主谋。"
    },
    {
        "track": "pr",
        "id": 1217,
        "text": "我并不怀疑确实有个女人进了你房间。",
        "hypothesis": "有个女人进了你房间。"
    },
    {
        "track": "pr",
        "id": 1218,
        "text": "可悲的是，连最亲近的人都没觉察我心里压着不爽。",
        "hypothesis": "我心里没有压着不爽。"
    },
    {
        "track": "pr",
        "id": 1219,
        "text": "二十日的周报是根据政府的统计写的，同样未加考虑，未做调查，就认为工作都已经做好了。",
        "hypothesis": "工作都已经做好了。"
    },
    {
        "track": "pr",
        "id": 1220,
        "text": "我在落笔的时候甚至都没有察觉到我的数学老师她不是个坏人。",
        "hypothesis": "我的数学老师她不是个坏人。"
    },
    {
        "track": "pr",
        "id": 1221,
        "text": "那个躲在树丛后的孩子正悄悄窥看邻居家的园丁修剪那棵巨大的橡树。",
        "hypothesis": "邻居家的园丁在修剪那棵巨大的橡树。"
    },
    {
        "track": "pr",
        "id": 1222,
        "text": "他们从不买衣服，几乎不去商场，平时从节省一滴水、一粒米做起，有钱舍不得用，有条件不知道享受，甚至被笑话成“最抠门的人”。",
        "hypothesis": "他们是最抠门的人。"
    },
    {
        "track": "pr",
        "id": 1223,
        "text": "《宠物之声》被广泛地认为是西方流行乐史上最具影响力的专辑之一。",
        "hypothesis": "《宠物之声》是西方流行乐史上最具影响力的专辑之一。"
    },
    {
        "track": "pr",
        "id": 1224,
        "text": "结束旅行后，他反思自己在旅途中对家人的关心太少，心里很不好受。",
        "hypothesis": "他在旅途中对家人的关心太少。"
    },
    {
        "track": "pr",
        "id": 1225,
        "text": "在安理会的非法决议中所规定的行动，是非法的。我们过去不曾承认那些行动，我们现在不承认而且永远也不会承认那些行动是合法的。",
        "hypothesis": "那些行动是合法的。"
    },
    {
        "track": "pr",
        "id": 1226,
        "text": "面对那些在灾难面前依然挥霍无度的富豪，许多市民讥讽他们的生活方式极其丑陋且缺乏基本的人性。",
        "hypothesis": "在灾难面前依然挥霍无度的富豪的生活方式不极其丑陋，且不缺乏基本的人性。"
    },
    {
        "track": "pr",
        "id": 1227,
        "text": "植物学家仔细端详叶片，辨别出这株珍稀兰花的品种属于石斛属。",
        "hypothesis": "这株珍稀兰花的品种属于石斛属。"
    },
    {
        "track": "pr",
        "id": 1228,
        "text": "现在有些人说我们店员工会太狠，说纠察队太强横了，他们不想想那些反动店东多么可恶；他们要歇业，藏起货物来，饿死我们，饿死全城的人！",
        "hypothesis": "那些反动店东非常可恶。"
    },
    {
        "track": "pr",
        "id": 1229,
        "text": "第二天，窗上刚麻麻亮，杨效忠醒来，披好衣服出门，就看见海明领着社员出发了。",
        "hypothesis": "海明没有领着社员出发。"
    },
    {
        "track": "pr",
        "id": 1230,
        "text": "他忘记要关窗户了，半夜突然下起了雨才想起来。",
        "hypothesis": "他关窗户了。"
    },
    {
        "track": "pr",
        "id": 1231,
        "text": "我们看见那是一架美国海军飞机。",
        "hypothesis": "那不是一架美国海军飞机。"
    },
    {
        "track": "pr",
        "id": 1232,
        "text": "他自己痛苦固然痛苦，却没有想象到有这么多人关心他。",
        "hypothesis": "没有许多人关心他。"
    },
    {
        "track": "pr",
        "id": 1233,
        "text": "拜天地的时候儿女都盖着盖头，新郎瞧不见新娘是一只眼。",
        "hypothesis": "新娘是一只眼。"
    },
    {
        "track": "pr",
        "id": 1234,
        "text": "面对这种毫无根据的指责和充满恶意的揣测，老实巴交的老张接受不了自己的清白名声被随意地践踏。",
        "hypothesis": "老张的清白名声被随意地践踏。"
    },
    {
        "track": "pr",
        "id": 1235,
        "text": "冲突各方应反思暴力事件给阿富汗人民带来的伤害，采取果断行动，尽早回到谈判桌前。",
        "hypothesis": "反思暴力事件没有给阿富汗人民带来伤害。"
    },
    {
        "track": "pr",
        "id": 1236,
        "text": "于是，他认真分析了健康人与病人机体内部的差异性，认识到，在自己头皮上针刺，针感不强，并不能断定在病人头皮上扎针也针感不强。",
        "hypothesis": "在病人头皮上扎针的针感不强。"
    },
    {
        "track": "pr",
        "id": 1237,
        "text": "那天，我察觉到了父亲的声音有些犹豫，但他还是答应了，并给我们两枚硬币。",
        "hypothesis": "父亲的声音没有犹豫。"
    },
    {
        "track": "pr",
        "id": 1238,
        "text": "而你的不配合却总在破坏他的自信，他当然会不高兴了，因为他觉得总是证明不了你们是真正的恋人关系。",
        "hypothesis": "你们是真正的恋人关系。"
    },
    {
        "track": "pr",
        "id": 1239,
        "text": "国际社会纷纷谴责这种背弃人道主义原则的行为极其残忍，完全无视了平民的基本生存权利。",
        "hypothesis": "这种背弃人道主义原则的行为不残忍，没有完全无视平民的基本生存权利。"
    },
    {
        "track": "pr",
        "id": 1240,
        "text": "面包饼干类食品易消化，所以，面包饼干类食品对消化道疾病患者的肠胃有益。不过，饼干一般被指认为垃圾食品。无事，少吃为好。",
        "hypothesis": "饼干是垃圾食品。"
    },
    {
        "track": "pr",
        "id": 1241,
        "text": "老张自知自己身体不好，不再像年轻时那样拼命工作。",
        "hypothesis": "老张身体好。"
    },
    {
        "track": "pr",
        "id": 1242,
        "text": "考古学家通过对地层堆积物的碳十四测年分析，判定这座古城遗址的建造年代可以追溯到三千多年前的商周时期。",
        "hypothesis": "这座古城遗址的建造年代不可以追溯到三千多年前的商周时期。"
    },
    {
        "track": "pr",
        "id": 1243,
        "text": "我偷看到父亲的眼角流下了伤心的泪水，我知道父亲为了我牺牲了他自己的一生。",
        "hypothesis": "父亲的眼角流下了伤心的泪水。"
    },
    {
        "track": "pr",
        "id": 1244,
        "text": "经过对现场遗留的脚印深度、步幅间距以及泥土翻动痕迹的细致比对，刑侦专家最终断定那名嫌疑人在案发当晚曾独自潜入过这间废弃的仓库。",
        "hypothesis": "那名嫌疑人在案发当晚曾独自潜入过这间废弃的仓库。"
    },
    {
        "track": "pr",
        "id": 1245,
        "text": "因此你就不能理解俄罗斯并不是在神秘主义，苦行主义，或处敬主义里面看到了自己的拯救，而是在文化，文明，和人道的胜利上看到了自我解放的道路。",
        "hypothesis": "俄罗斯并不是在神秘主义，苦行主义，或处敬主义里面看到了自己的拯救，而是在文化、文明和人道的胜利上看到了自我解放的道路。"
    },
    {
        "track": "pr",
        "id": 1246,
        "text": "分别于1990年4月和1991年4月进入太空的“哈勃”天文望远镜和伽马射线探测器以及其他一些观测仪器也对宇宙的结构和演化进行了观测，取得了大量成果。这些成果认为宇宙将一直膨胀下去。",
        "hypothesis": "宇宙不会一直膨胀下去。"
    },
    {
        "track": "pr",
        "id": 1247,
        "text": "安子指着熊义笑道：“就是和他刚才一样，都喜哄着人图自己开心。你没听他说的吗？你丈夫哄你，说讨了人，亏你聪明悟出是假的。熊先生当面哄你，如何这信以为真？你问熊先生，看他的话毕竟是真是假？”",
        "hypothesis": "你丈夫讨了人不是假的。"
    },
    {
        "track": "pr",
        "id": 1248,
        "text": "50岁的谢兰，当社区干部已经17年了。在此之前她搞过运输队，开过皮鞋厂，是人们眼中的“女强人”；当上社区干部后，因为工作敢碰硬，办事讲原则，干练中有股子不服输的倔强，又有人说她是“铁豌豆”。但谢兰自己并未想到，这两年的工作会这么难。",
        "hypothesis": "这两年的工作很难。"
    },
    {
        "track": "pr",
        "id": 1249,
        "text": "今儿早起，你们令郎就和我说了，吃早饭的时候儿我就去了一次，偏偏儿的遇见他不在家，才交晌午我又去了，没到他上房之前就听见里头说啊笑的声儿，因为这上头，我把窗户纸儿舔破了，从窗户眼儿里往里一瞧，看见这个给那个斟酒，那个给这个回敬，正搅在一处儿吃喝热闹了。",
        "hypothesis": "吃早饭的时候儿他不在家。"
    },
    {
        "track": "pr",
        "id": 1250,
        "text": "直到聚会上朋友半开玩笑地提醒，我才惊觉自己竟然完全没有发现自己在这段感情里变得极其患得患失。",
        "hypothesis": "我在这段感情里没有变得极其患得患失。"
    },
    {
        "track": "pr",
        "id": 1251,
        "text": "陈老先生吃过点心，到院中看花草。他并不爱花，可是每遇到它们，他不能不看，而且在自己家中是早晚必找上它们去看一会儿，因为诗中常常描写花草霜露，他可以不爱花，而不能表示自己不懂得诗。",
        "hypothesis": "陈老先生自己懂得诗。"
    },
    {
        "track": "pr",
        "id": 1252,
        "text": "有一位爸爸，经常批评上中学的儿子学习不认真，不用心完成作业，武断地认为他不是读书的料。",
        "hypothesis": "他不是读书的料。"
    },
    {
        "track": "pr",
        "id": 1253,
        "text": "“妙极了！”我不自禁地赞叹着。这时詹水晶并未发现身边有人，他仍然聚精会神，贴近车床，盯住车刀，不时拿起“样板”比量着，他的心已同整部机器、整个“活”融合在一起了。",
        "hypothesis": "詹水晶身边有人。"
    },
    {
        "track": "pr",
        "id": 1254,
        "text": "据路透社讯，日本的报纸普遍地认为吉田的新内阁是不稳固的。",
        "hypothesis": "吉田的新内阁是不稳固的。"
    },
    {
        "track": "pr",
        "id": 1255,
        "text": "如花似玉的旋律令人应接不暇，而又如此自然地交响化了。是这样的纯朴而流美，舒伯特之后唯有他一人吧？完全可以评他深刻不够，决不会嫌他矫揉做作。",
        "hypothesis": "他不矫揉做作。"
    },
    {
        "track": "pr",
        "id": 1256,
        "text": "媒体记者多方求证并查阅内部文件，查实这家知名企业在宣传中夸大了产品功效，其营销手段不仅虚伪而且对消费者极不负责任。",
        "hypothesis": "这家知名企业在宣传中夸大了产品功效。"
    },
    {
        "track": "pr",
        "id": 1257,
        "text": "站在观景台上的游客们看到远处的火山口缓缓升起了巨大的灰色烟柱。",
        "hypothesis": "远处的火山口缓缓升起了巨大的灰色烟柱。"
    },
    {
        "track": "pr",
        "id": 1258,
        "text": "司法官猜想她大概不会讲丹麦文，因此把他的要求又用德文讲了一遍。他的口音和他的装束使得老板娘相信他是一个外国人。老板娘马上懂得了他有些不舒服，因此倒了一杯水给他喝。",
        "hypothesis": "司法官没有不舒服。"
    },
    {
        "track": "pr",
        "id": 1259,
        "text": "他站在角落里嘀咕这帮人做事太不地道，明明答应了帮忙却临阵脱逃。",
        "hypothesis": "这帮人做事太不地道。"
    },
    {
        "track": "pr",
        "id": 1260,
        "text": "直到法庭出示了关键证据，被告人才被迫得知自己的同伙早已在审讯中供出了所有细节。",
        "hypothesis": "被告人的同伙已在审讯中供出了所有细节。"
    },
    {
        "track": "pr",
        "id": 1261,
        "text": "他眼神闪烁，却还是佯言自己内心对这场比赛的输赢毫不在意。",
        "hypothesis": "他内心对这场比赛的输赢毫不在意。"
    },
    {
        "track": "pr",
        "id": 1262,
        "text": "一般认为蛛网理论的典型例子，是英国养猪产业的循环周期。我们作了一项统计研究凋查，结果一如我们所猜想，英国的养猪业者并没有假设目前的价格会在未来维持不变。当价格高得异常时，他们预期价格会下跌；而当价格低得离谱时，他们预期未来价格会上扬。",
        "hypothesis": "目前的价格会在未来维持不变。"
    },
    {
        "track": "pr",
        "id": 1263,
        "text": "其实作为学生的我在专业领域内心一直不敢妄称是张老师的学生，很多时候因为自己不够努力进取甚至不敢直面老师。 ",
        "hypothesis": "我不是张老师的学生。"
    },
    {
        "track": "pr",
        "id": 1264,
        "text": "其实我还是想相信我的身体没有问题。",
        "hypothesis": "我的身体有问题。"
    },
    {
        "track": "pr",
        "id": 1265,
        "text": "当然，我不敢说这一定是“对世界所能作的最好的描绘”，更不能断言这位中篇小说作者便是“诚实的天才”。",
        "hypothesis": "这位中篇小说作者不是“诚实的天才”。"
    },
    {
        "track": "pr",
        "id": 1266,
        "text": "指挥部在接收到前线侦察兵传回的情报后，判明敌方主力部队已经在昨夜悄然渡过了阵地前的河流。",
        "hypothesis": "敌方主力部队没有在昨夜渡过了阵地前的河流。"
    },
    {
        "track": "pr",
        "id": 1267,
        "text": "她凝视着那幅画，辨别出画家在色彩运用上有着独特的情感表达。",
        "hypothesis": "画家在色彩运用上有着独特的情感表达。"
    },
    {
        "track": "pr",
        "id": 1268,
        "text": "石苞至此都没有怨恨司马炎不信任他，反而为无法做好职位为而感到耻辱。",
        "hypothesis": "司马炎不信任他。"
    },
    {
        "track": "pr",
        "id": 1269,
        "text": "调查组深入事故现场进行勘查，最终查出操作工人在启动机器前并未按照规程检查安全阀门的状态，从而引发了这场严重的爆炸。",
        "hypothesis": "操作工人在启动机器前按照规程检查了安全阀门的状态。"
    },
    {
        "track": "pr",
        "id": 1270,
        "text": "上次咳嗽在输了几天水，孩子打针都打怕了，我也不愿意看见孩子那么的受罪，大家有什么好的意见和办法，能让孩子食疗止咳，我在这里谢谢大家了！",
        "hypothesis": "孩子不很受罪。"
    },
    {
        "track": "pr",
        "id": 1271,
        "text": "北约秘书长罗伯逊5日表示，北约将尽快向意大利和其它欧盟成员国提供贫铀弹的细节资料，但他并未否认贫铀弹污染会伤害人体。",
        "hypothesis": "贫铀弹污染不会伤害人体。"
    },
    {
        "track": "pr",
        "id": 1272,
        "text": "分别于1990年4月和1991年4月进入太空的“哈勃”天文望远镜和伽马射线探测器以及其他一些观测仪器也对宇宙的结构和演化进行了观测，取得了大量成果。这些成果较为一致地认为宇宙将一直膨胀下去。",
        "hypothesis": "宇宙将一直膨胀下去。"
    },
    {
        "track": "pr",
        "id": 1273,
        "text": "如果是一个社会现象的话，这个实际上黑白是分明的，从分析当事每个人的动机就可以看到会采取什么样的态度。就是搞考级的老师让他们扪心自问，他内心也不会认同这些东西对儿童有积极作用。",
        "hypothesis": "这些东西对儿童有积极作用。"
    },
    {
        "track": "pr",
        "id": 1274,
        "text": "母亲的皱纹更深的刻在脸上了，叔父的胡子更乱的蔓延在脸上了，弟弟们拖着鼻涕和衣服的缺襟，露着大的眼珠和瘦削的两颊。一瞥中我留意到这灯正是从前在柿场上用的煤油灯，添上的是一条熏黑通弯铁丝，和玻璃瓶上的两条裂缝。",
        "hypothesis": "这灯不是从前在柿场上用的煤油灯。"
    },
    {
        "track": "pr",
        "id": 1275,
        "text": "党委工作制要求领导人善于听取全体委员的意见，考虑他们的建议，勇敢地接受对自己缺点的批评。他不能认为批评指责有损自己的威信，不得把个人自尊心置于事业的利益之上。",
        "hypothesis": "批评指责不会损害自己的威信。"
    },
    {
        "track": "pr",
        "id": 1276,
        "text": "命运使我自十九岁时起就承担了高棉国家的职责，我当然不会抱怨这半个世纪所度过的生活是平淡的、平凡的和没有趣味的。",
        "hypothesis": "这半个世纪所度过的生活不是平淡的、平凡的和没有趣味的。"
    },
    {
        "track": "pr",
        "id": 1277,
        "text": "今年五月，工人们组织篮球队要和外面球队比赛，当时他们向我们借运动衣，我们机械地认为这是只发给代表队的，就没借给他们。",
        "hypothesis": "运动衣是只发给代表队的。"
    },
    {
        "track": "pr",
        "id": 1278,
        "text": "尽管市场波动剧烈，这位资深分析师依然担保该基金组合在下个季度末会实现正收益。",
        "hypothesis": "该基金组合在下个季度末会实现正收益。"
    },
    {
        "track": "pr",
        "id": 1279,
        "text": "在长达数小时的审讯之后，他终于承认在深夜潜入了博物馆并窃走了那幅珍贵的油画。",
        "hypothesis": "他没有在深夜潜入博物馆并窃走那幅珍贵的油画。"
    },
    {
        "track": "pr",
        "id": 1280,
        "text": "报告指出，美国不同性别、年龄、族裔人群的自杀率都在上升，且超过一半的自杀死亡人员并没有被诊断出患有精神疾病。",
        "hypothesis": "超过一半的自杀死亡人员患有精神疾病。"
    },
    {
        "track": "pr",
        "id": 1281,
        "text": "他针对敌人所散布的种种反动谣言，要求部队不管走到哪儿，都要把红军的优良作风带到哪儿，让新区人民群众晓得红军是一支纪律严明的工农队伍。",
        "hypothesis": "红军不是一支纪律严明的工农队伍。"
    },
    {
        "track": "pr",
        "id": 1282,
        "text": "赵文正确地指出李秀成有动摇乞降的叛变行为，不同意以伪降说为他辩解，并指出对他的乞降问题应该予以严肃的批判。",
        "hypothesis": "李秀成没有动摇乞降的叛变行为。"
    },
    {
        "track": "pr",
        "id": 1283,
        "text": "这充分说明，我们不能把一种理论观点和学术成果当成“唯一准则”，不能企图用一种模式来改造整个世界。",
        "hypothesis": "我们不可以用一种模式来改造整个世界。"
    },
    {
        "track": "pr",
        "id": 1284,
        "text": "除非你故意不想知道我们的祖国曾经走过多么艰难困苦的道路。",
        "hypothesis": "我们的祖国曾经走过很艰难困苦的道路。"
    },
    {
        "track": "pr",
        "id": 1285,
        "text": "现有的科学技术还没有证明人对草原自然生态系统具有控制能力。",
        "hypothesis": "人对草原自然生态系统不具有控制能力。"
    },
    {
        "track": "pr",
        "id": 1286,
        "text": "安子指着熊义笑道：“就是和他刚才一样，都喜哄着人图自己开心。你没听他说的吗？你丈夫哄你，说讨了人，亏你聪明悟出是假的。熊先生当面哄你，如何这信以为真？你问熊先生，看他的话毕竟是真是假？”",
        "hypothesis": "你丈夫讨了人是假的。"
    },
    {
        "track": "pr",
        "id": 1287,
        "text": "他们居住在一个不通电、不通公路的小土房里，两个儿子都在外地打工。但他们并未觉得生活很苦，每天踏踏实实地耕耘生活，让自己的玉米地收成更好，因为他们有让生活更美好的梦想。",
        "hypothesis": "他们的生活很苦。"
    },
    {
        "track": "pr",
        "id": 1288,
        "text": "那些缺乏实地调研的评论家常常妄言这种传统的耕作方式极其落后，完全不符合现代农业的发展潮流。",
        "hypothesis": "这种传统的耕作方式不极其落后，符合现代农业的发展潮流。"
    },
    {
        "track": "pr",
        "id": 1289,
        "text": "罗比以超过三百万的专辑销量，被估计是拉丁美洲最畅销的非拉丁歌手。",
        "hypothesis": "罗比是拉丁美洲最畅销的非拉丁歌手。"
    },
    {
        "track": "pr",
        "id": 1290,
        "text": "合同最后一页上双方代表的签字，标示着这项跨越十年的商业谈判画上了句号。",
        "hypothesis": "这项跨越十年的商业谈判画上了句号。"
    },
    {
        "track": "pr",
        "id": 1291,
        "text": "毋庸讳言，我国各级干部的薪水相对来说并不高，但这个群体的生活水准仍在社会中线之上，而且比较稳定和有保障，就像井里的水，不是很多，但一直有。而不少困难群众还在为生计奔波、为治病费用头疼。这可以解释为什么群众从不原谅贪官，难以理解那些人为何要不顾一切地作奸犯科，甚至赌上身家性命。",
        "hypothesis": "那些人未曾不顾一切地作奸犯科。"
    },
    {
        "track": "pr",
        "id": 1292,
        "text": "随着更多内部邮件被公开披露，媒体记者查实那位高管早在项目启动初期就已经知晓潜在的环境污染风险。",
        "hypothesis": "那位高管早在项目启动初期就已经知晓潜在的环境污染风险。"
    },
    {
        "track": "pr",
        "id": 1293,
        "text": "我真的很敬佩我的父亲在他近80岁高龄时还不甘寂寞，变法维新。",
        "hypothesis": "我的父亲在他近80岁高龄时甘于寂寞，不变法维新。"
    },
    {
        "track": "pr",
        "id": 1294,
        "text": "他梦到千年前的古战场重新燃起烽火，士兵们的呐喊声震落了书架上的灰尘。",
        "hypothesis": "千年前的古战场没有重新燃起烽火，士兵们的呐喊声没有震落书架上的灰尘。"
    },
    {
        "track": "pr",
        "id": 1295,
        "text": "但是，电影如何能够让观众感到兴奋呢？我想，首先是不能假定大家都关心英国文学、英国的历史。",
        "hypothesis": "大家不是都关心英国文学、英国的历史。"
    },
    {
        "track": "pr",
        "id": 1296,
        "text": "她反复思考后理解自己内心真正想要的是平静的生活。",
        "hypothesis": "她内心真正想要的不是平静的生活。"
    },
    {
        "track": "pr",
        "id": 1297,
        "text": "虽然迪萨纳亚克并未否认某些艺术在象征和认知方面煞费苦心，但是这些观念在她解释艺术起源和艺术至高无上的审美价值时，并未以特征的方式显示出来。",
        "hypothesis": "某些艺术在象征和认知方面煞费苦心。"
    },
    {
        "track": "pr",
        "id": 1298,
        "text": "我不想伤害她，但是我容忍不了她继续在你身边。",
        "hypothesis": "她正在你身边。"
    },
    {
        "track": "pr",
        "id": 1299,
        "text": "当前，一些攻击披上了意识形态偏见的外衣。这种论点的致命缺陷在于它忽视了历史：美国就一直被其民众诟病危机处置不当。",
        "hypothesis": "美国一直危机处置得当。"
    },
    {
        "track": "pr",
        "id": 1300,
        "text": "我见到这些所谓的“问题”学生骨子里充满了想得到关注、被尊重的渴望，这份渴望比其他人更强烈，无非在现实里常常得不到接纳和理解，反被责备是他们自己不进取。",
        "hypothesis": "这些所谓的“问题”学生不是自己不进取。"
    },
    {
        "track": "pr",
        "id": 1301,
        "text": "路过工地的行人看见巨大的塔吊缓缓转动臂膀，将一捆捆钢筋准确无误地吊运到三十层高的楼板上。",
        "hypothesis": "塔吊将钢筋吊运到了三十层高的楼板上。"
    },
    {
        "track": "pr",
        "id": 1302,
        "text": "战争贩子正在而且将会继续用尽一切力量来破坏和削弱我们的运动。和平运动已不止一次地被说是一个宣传活动。然而亿万支持我们的要求的人民证明了我们的运动的纯正。",
        "hypothesis": "和平运动不是一个宣传活动。"
    },
    {
        "track": "pr",
        "id": 1303,
        "text": "就拿之前阿马蒂亚·库马尔·森所举的例子来说，公共选择理论并没有假设每个人随时都想着要趁机占他人便宜或损害他人利益，而是假设人的行为是理性的，也因此本地人指点外地人到正确的火车站其实是更为理性的选择。",
        "hypothesis": "每个人随时都想着要趁机占他人便宜或损害他人利益。"
    },
    {
        "track": "pr",
        "id": 1304,
        "text": "在积水潭医院烧伤科病床上，面目全非的陈果几乎不能说话了。看到她焦残的双手和脸部黑色的焦痂，谁都无法想象她曾是音乐学院一名弹琵琶的漂亮女孩。",
        "hypothesis": "陈果曾是音乐学院一名弹琵琶的漂亮女孩。"
    },
    {
        "track": "pr",
        "id": 1305,
        "text": "高耀洁做了一个重要的决定：谢绝给病人看病，倾全力宣传防治艾滋病。但那时，高耀洁并没有想到这条路竟如此坎坷、如此艰难！",
        "hypothesis": "谢绝给病人看病，倾全力宣传防治艾滋病，这条路不非常坎坷、不非常艰难。"
    },
    {
        "track": "pr",
        "id": 1306,
        "text": "这次实验意外地暴露出新型催化剂的物理特性在高温高压环境下极不稳定。",
        "hypothesis": "新型催化剂的物理特性在高温高压环境下极不稳定。"
    },
    {
        "track": "pr",
        "id": 1307,
        "text": "尽管车后的手套箱里有急救箱，但她没有试图立即上绷带，迷糊中她指望流血能洗净伤口。",
        "hypothesis": "她没有立即上绷带。"
    },
    {
        "track": "pr",
        "id": 1308,
        "text": "妈妈却不得不表扬自己的儿子能干。",
        "hypothesis": "自己的儿子能干。"
    },
    {
        "track": "pr",
        "id": 1309,
        "text": "有一位爸爸，经常批评上中学的儿子学习不认真，不用心完成作业，认为他不是读书的料。",
        "hypothesis": "他是读书的料。"
    },
    {
        "track": "pr",
        "id": 1310,
        "text": "为了补贴修建超支，为了解决房屋问题，我没有请示上级，就作了这样轻率的错误的决定，没有考虑浪费国家木材是严重错误。",
        "hypothesis": "浪费国家木材是严重错误。"
    },
    {
        "track": "pr",
        "id": 1311,
        "text": "投资者理所当然地认为国债投资可靠，比储蓄利率高等，因此就成为一种惯性购买行为。",
        "hypothesis": "国债投资可靠，比储蓄利率高等。"
    },
    {
        "track": "pr",
        "id": 1312,
        "text": "她眼睁睁看见三子跳了楼，绝没有想她和大家那么快就缓过来了，好像就是睡一觉的工夫，第二天再没人提到三子。",
        "hypothesis": "她和大家那么快就缓过来了。"
    },
    {
        "track": "pr",
        "id": 1313,
        "text": "最后一日，她安静下去了，到得次日早晨才被人发现她已安睡在自己床上，而且永久不再醒来了，还是满面脂粉，一头柳叶桃的红花。",
        "hypothesis": "她已经去世。"
    },
    {
        "track": "pr",
        "id": 1314,
        "text": "张麦麦学的很有兴趣，虽说把臂都练肿了，可是还不觉得很疼楚疲劳。",
        "hypothesis": "张麦麦很疼楚疲劳。"
    },
    {
        "track": "pr",
        "id": 1315,
        "text": "2011年，哥伦比亚大学被检举故意提交错误的艾滋病研究项目人员名单和项目进展信息，拨出经费花在与项目无关的事务上。",
        "hypothesis": "哥伦比亚大学故意提交错误的艾滋病研究项目人员名单和项目进展信息，拨出经费花在与项目无关的事务上。"
    },
    {
        "track": "pr",
        "id": 1316,
        "text": "伦纳德再一次地没有意识到佩妮私下里对于伦纳德和别人约会很不高兴，她最终崩溃并且大哭。",
        "hypothesis": "佩妮私下里对于伦纳德和别人约会没有很不高兴。"
    },
    {
        "track": "pr",
        "id": 1317,
        "text": "通过拦截并破译敌方的加密通讯信号，情报部门探知到敌军主力部队正在向边境地区秘密集结。",
        "hypothesis": "敌军主力部队没有在向边境地区秘密集结。"
    },
    {
        "track": "pr",
        "id": 1318,
        "text": "我很抱歉他竟然如此粗心。",
        "hypothesis": "他很粗心。"
    },
    {
        "track": "pr",
        "id": 1319,
        "text": "因为不正视历史，也就不会懂得今天国际社会存在的贫富差别，更不会懂得发展中国家谋发展是他们最重要的诉求。",
        "hypothesis": "今天国际社会存在贫富差别。"
    },
    {
        "track": "pr",
        "id": 1320,
        "text": "总的来说，齐格菲防线的宣传意义几乎和它的战略意义一样大，在相当长的时间里，它都被宣称为一条坚固的防线，一直影响到了1944年，但到了真的面对它的时候，无论是德国人还是盟军，都发现这条防线的大部分设计已经不符合当时的战场形势了，尽管它起到了阻滞盟军的作用，但显然不像德国人声称的那样坚不可摧。",
        "hypothesis": "齐格菲防线在相当长的时间里是一条坚固的防线。"
    },
    {
        "track": "pr",
        "id": 1321,
        "text": "大多数城镇居民并不接受本地文化掺入过多的外地文化，或者说过多外地人聚居。",
        "hypothesis": "本地文化没有掺入过多的外地文化。"
    },
    {
        "track": "pr",
        "id": 1322,
        "text": "小微哥微信上有个庞大的后宫团，有时候想要办个小活动福泽一下大家，却每次都被控诉独宠余剑铭一人。",
        "hypothesis": "小微哥独宠余剑铭一人。"
    },
    {
        "track": "pr",
        "id": 1323,
        "text": "考虑到水很凉，同志们不能长时间在水中干，就把大家分为3个班，每班10分钟，尽量在水中少呆。",
        "hypothesis": "水不凉。"
    },
    {
        "track": "pr",
        "id": 1324,
        "text": "“啊，我明白了。鸣凤自尽了，所以爷爷用婉儿代替。横竖在爷爷的眼睛里，丫头都不是人，可以由他当作礼物送来送去。……看不出鸣凤倒是一个烈性的女子，她倒做出这样的事情！”",
        "hypothesis": "鸣凤是一个烈性的女子。"
    },
    {
        "track": "pr",
        "id": 1325,
        "text": "我从不怀疑自己对他的爱是盲目的，是冲动的。",
        "hypothesis": "我对他的爱是盲目的，是冲动的。"
    },
    {
        "track": "pr",
        "id": 1326,
        "text": "要粮要地是农民的两大要求。进一步又了解到群众怕地主。",
        "hypothesis": "群众不怕地主。"
    },
    {
        "track": "pr",
        "id": 1327,
        "text": "初入职场的年轻人并不能理解这些资深工程师为何坚持在代码提交前进行如此繁琐且耗时的手动复查。",
        "hypothesis": "这些资深工程师在代码提交前没有进行非常繁琐且耗时的手动复查。"
    },
    {
        "track": "pr",
        "id": 1328,
        "text": "尽管两位人类学家的观点相互对立，一个认为文化的演化是独立的，另一个认为文化的演化是传播的，但他们都认为是科学革命推动了人类学的发展。",
        "hypothesis": "是科学革命推动了人类学的发展。"
    },
    {
        "track": "pr",
        "id": 1329,
        "text": "受害者的家属指责警方弄丢了那份能够证明被告无罪的关键证据。",
        "hypothesis": "警方弄丢了那份能够证明被告无罪的关键证据。"
    },
    {
        "track": "pr",
        "id": 1330,
        "text": "描红见台青一派天真，实在不愿相信她是一个坏女孩，只得也迎向前来。",
        "hypothesis": "台青是一个坏女孩。"
    },
    {
        "track": "pr",
        "id": 1331,
        "text": "许多员工已经厌倦同事之间那种虚伪而冷漠的相处模式。",
        "hypothesis": "同事之间的相处模式不虚伪也不冷漠。"
    },
    {
        "track": "pr",
        "id": 1332,
        "text": "于是，上官桀父子联合盖长公主、燕王刘旦以及辅政大臣桑弘羊等共同结成反对霍光的同盟，假托燕王名义趁霍光休假的时候向汉昭帝上书诬陷霍光有不臣之心，并内外接应，做好准备打算一举擒杀霍光，但时年仅十四岁的昭帝识破了他们的阴谋，不予理睬，并安抚霍光，且下令追查上书人的来历。",
        "hypothesis": "霍光有不臣之心。"
    },
    {
        "track": "pr",
        "id": 1333,
        "text": "政府在推行新的交通限行政策时没有考虑到偏远郊区居民乘坐公共交通存在困难，引发了广泛的社会争议。",
        "hypothesis": "偏远郊区居民乘坐公共交通不存在困难。"
    },
    {
        "track": "pr",
        "id": 1334,
        "text": "要是他们光凭着自己的感想和那个管家奶奶的报道来称道他的不人，而不参考任何其他资料，那么，哈福德郡那些认识他的人，简直辨别不出这是讲的达西先生。",
        "hypothesis": "这是讲的达西先生。"
    },
    {
        "track": "pr",
        "id": 1335,
        "text": "但此间舆论在肯定这些成果的同时，也客观地指出，南联盟不少民众仍有强烈的反美情绪，而美国的一些决策者对南联盟也有根深蒂固的偏见，加上两国间还存在一些诸如对科索沃战争的不同认识等难以在短期内解决的问题，南、美两国关系要想得到完全的改善，还有相当一段布满荆棘的路要走。",
        "hypothesis": "南联盟不少民众没有强烈的反美情绪。"
    },
    {
        "track": "pr",
        "id": 1336,
        "text": "那一天我去瞧他，我看见他瘦得一点肉没有，竟剩下骨头咯，在炕上倒气儿呢。",
        "hypothesis": "他瘦得一点肉没有。"
    },
    {
        "track": "pr",
        "id": 1337,
        "text": "你不晓得我心里很难受。我不是青年，我没有青春。",
        "hypothesis": "我心里不难受。"
    },
    {
        "track": "pr",
        "id": 1338,
        "text": "艺术作品中没有出现具体的年代标记，并不证明它是现代工匠伪造的赝品。",
        "hypothesis": "它是现代工匠伪造的赝品。"
    },
    {
        "track": "pr",
        "id": 1339,
        "text": "她尽管很疲惫，却还是装作精力充沛的样子，继续和朋友们玩耍。",
        "hypothesis": "她精力充沛。"
    },
    {
        "track": "pr",
        "id": 1340,
        "text": "虽然教练对队员们的体能训练提出了极高要求，但他不期待这群年轻选手能在明天的决赛中击败经验丰富的卫冕冠军。",
        "hypothesis": "这群年轻选手不能在明天的决赛中击败经验丰富的卫冕冠军。"
    },
    {
        "track": "pr",
        "id": 1341,
        "text": "他还说，自从第二次世界大战结束以来，在苏联已经有了许多变化，克里姆林的领袖们不想看到他们建立起来的一切被摧毁。",
        "hypothesis": "克里姆林的领袖们建立起来的一切已经被摧毁了。"
    },
    {
        "track": "pr",
        "id": 1342,
        "text": "我不敢担保那些将“无为”奉为最高信条的同事不因此坐立不安。至于福古贝，你们知道他由于亲法政策而受到猛烈抨击，这使他很难过，何况此公心地善良，而且很敏感。",
        "hypothesis": "那些将“无为”奉为最高信条的同事不因此坐立不安。"
    },
    {
        "track": "pr",
        "id": 1343,
        "text": "我向领导抱怨房子太小，3个房间紧挨在一起，褥子就铺在地上，什么家具都没有。",
        "hypothesis": "房子不小。"
    },
    {
        "track": "pr",
        "id": 1344,
        "text": "金波先生没有奢望这本书能给人启蒙教化，或成为后来者文学创作的指南。",
        "hypothesis": "这本书能给人启蒙教化。"
    },
    {
        "track": "pr",
        "id": 1345,
        "text": "他确实并不残暴，也并不虚伪，他既不想也不能意识到自己就是坑害了女儿的第一把手，归根结底其实他也只是依附了他那时代与社会的驯服工具而已。",
        "hypothesis": "他自己就是坑害了女儿的第一把手。"
    },
    {
        "track": "pr",
        "id": 1346,
        "text": "他当时还庆幸自己终于度过了这一关，却不知道自己再也走不出来了。",
        "hypothesis": "他走得出来。"
    },
    {
        "track": "pr",
        "id": 1347,
        "text": "此前，我还一直觉得小姜是个内向的人，课上总低着头，也很少发言。",
        "hypothesis": "小姜不是个内向的人。"
    },
    {
        "track": "pr",
        "id": 1348,
        "text": "马来西亚总理纳吉布向大马议会表示，马政府没有企图向失联乘客家属隐瞒信息。",
        "hypothesis": "马政府不曾向失联乘客家属隐瞒信息。"
    },
    {
        "track": "pr",
        "id": 1349,
        "text": "乔正天在家人一半不知情，一半不认账的情势下，被认定是个无情冷血，辜恩寡义的大独裁者。",
        "hypothesis": "乔正天不是个无情冷血、辜恩寡义的大独裁者。"
    },
    {
        "track": "pr",
        "id": 1350,
        "text": "我们真不敢称自己是腕，也没有在网上主动做过任何的宣传，一些简单新鲜的家常菜，不算多美味，但是能让来到这里的客人感受到我们的用心和发自内心的真诚，就像接待自家远方的亲戚朋友，舒舒服服在捞海坞吃了一顿饱饭。",
        "hypothesis": "我们不是腕。"
    },
    {
        "track": "pr",
        "id": 1351,
        "text": "上帝并不明白自己在作梦，或者梦在作弄自己。",
        "hypothesis": "自己在作梦。"
    },
    {
        "track": "pr",
        "id": 1352,
        "text": "在之前，Life已因涉嫌假赛遭警方逮捕调查，并已坐实假赛罪名。而之前因身体原因弃权本赛季韩国所有比赛的Bbyong也一直被猜测涉嫌参与假赛。",
        "hypothesis": "Bbyong没有参与假赛。"
    },
    {
        "track": "pr",
        "id": 1353,
        "text": "但是，官方不愿透露伊格尔伯格是否会见了诺列加，据认为，美国向教廷施加了压力，并在教皇特使贝尔洛克科的帮助下，劝说诺列加自行离开梵蒂冈使馆。",
        "hypothesis": "伊格尔伯格会见了诺列加。"
    },
    {
        "track": "pr",
        "id": 1354,
        "text": "这位经验丰富的工程师在检查完所有数据后，自信团队能够在预定时间内完成大桥的主体结构施工。",
        "hypothesis": "团队不能在预定时间内完成大桥的主体结构施工。"
    },
    {
        "track": "pr",
        "id": 1355,
        "text": "刚才我没看到他在田里干农活，只看到他在田里逮虫子。",
        "hypothesis": "他在田里干农活。"
    },
    {
        "track": "pr",
        "id": 1356,
        "text": "他说，除了帝国主义者以外，谁也不会谴责印度尼西亚收复自己的领土是进行侵略。",
        "hypothesis": "印度尼西亚收复自己的领土是进行侵略。"
    },
    {
        "track": "pr",
        "id": 1357,
        "text": "他这句话，分明是卖弄他有家私，带着他瞧我们不起。",
        "hypothesis": "他有家私。"
    },
    {
        "track": "pr",
        "id": 1358,
        "text": "站在高处的瞭望塔上，哨兵感觉远处的地平线上有一群骑兵正向营地快速逼近。",
        "hypothesis": "远处的地平线上有一群骑兵正向营地快速逼近。"
    },
    {
        "track": "pr",
        "id": 1359,
        "text": "虽然也有人表示谨慎的“欢迎”，但多数人对勃列日涅夫“建议”的真实意图深怀戒心，甚至指出，这是欺骗和讹诈。",
        "hypothesis": "这是欺骗和讹诈。"
    },
    {
        "track": "pr",
        "id": 1360,
        "text": "由于爱护关心他们，保罗不愿看见他们的思想受到腐化，所以他劝戒说：“你们总要自己省察有信心没有，也要自己试验。”",
        "hypothesis": "他们的思想没有受到腐化。"
    },
    {
        "track": "pr",
        "id": 1361,
        "text": "对方在十一日声称：“联合国军代表团并不深信双方司令官的任何建议是朝鲜的军事停战所必需的。”",
        "hypothesis": "双方司令官的任何建议是朝鲜的军事停战所必需的。"
    },
    {
        "track": "pr",
        "id": 1362,
        "text": "我还明白：当一个国家还老无所养，病无所医时，再多的金牌也证明不了你不再是东亚病夫！",
        "hypothesis": "你不再是东亚病夫。"
    },
    {
        "track": "pr",
        "id": 1363,
        "text": "在金库设计时，原来并未考虑允许人们进来参观。但金库建成后，国内外银行界的同行纷纷要求参观，遂决定开设这一“旅游”项目，让世界各国银行界的同行进一步了解美国和美元。",
        "hypothesis": "金库原来允许人们进来参观。"
    },
    {
        "track": "pr",
        "id": 1364,
        "text": "气象卫星传回的高分辨率数据证实那股正在形成的热带气旋中心气压已经达到了历史同期的最低值。",
        "hypothesis": "那股正在形成的热带气旋中心气压已经达到了历史同期的最低值。"
    },
    {
        "track": "pr",
        "id": 1365,
        "text": "我并不后悔三十多年前离开花花世界的香港，自愿来到当时吹起一阵《清风》的艰苦的北方。",
        "hypothesis": "我没有三十多年前离开花花世界的香港。"
    },
    {
        "track": "pr",
        "id": 1366,
        "text": "气象卫星传回的高分辨率数据证实那股正在形成的热带气旋中心气压已经达到了历史同期的最低值。",
        "hypothesis": "那股正在形成的热带气旋中心气压没有达到历史同期的最低值。"
    },
    {
        "track": "pr",
        "id": 1367,
        "text": "漫步在古老街道上的游客没意识到脚下这块看似普通的石板其实是千年前古城墙地基的一部分。",
        "hypothesis": "脚下这块看似普通的石板其实是千年前古城墙地基的一部分。"
    },
    {
        "track": "pr",
        "id": 1368,
        "text": "有人悲叹高质量的艺术是阳春白雪，指责观众喜欢看粗俗低劣的东西。",
        "hypothesis": "高质量的艺术是阳春白雪。"
    },
    {
        "track": "pr",
        "id": 1369,
        "text": "许多传统学者不认可年轻一代提出的这套基于大数据的社会分层模型能够准确反映当前城乡流动的真实状况。",
        "hypothesis": "年轻一代提出的这套基于大数据的社会分层模型能够准确反映当前城乡流动的真实状况。"
    },
    {
        "track": "pr",
        "id": 1370,
        "text": "他根本不会晓得，我是故意罚他的。",
        "hypothesis": "我不是故意罚他的。"
    },
    {
        "track": "pr",
        "id": 1371,
        "text": "你没有瞧见我想得都快要发狂了！",
        "hypothesis": "我想得都快要发狂了。"
    },
    {
        "track": "pr",
        "id": 1372,
        "text": "这位年轻的学者在发表那篇轰动学界的论文之前，自以为他提出的理论模型能够完美解释所有观测到的异常数据，却未曾料到后续的实验结果会彻底推翻他的核心假设。",
        "hypothesis": "这位年轻的学者提出的理论模型能够完美解释所有观测到的异常数据。"
    },
    {
        "track": "pr",
        "id": 1373,
        "text": "其实，对于我来说，沫沫道歉了，我固然会认为他是个好孩子；但沫沫不道歉，我也不会认定他就是个坏孩子。相反的是，朋友的声色俱厉，我认为有点过了。",
        "hypothesis": "他就是个坏孩子。"
    },
    {
        "track": "pr",
        "id": 1374,
        "text": "面对一些踌躇满志的书画投资者，笔者虽不会断言杠杆资金不能用。但是，面对艺术品投资行业客观存在的各种短板，我们确实要好好反思一下，当最糟糕的情况出现后，我们有能力避开这些短板、找到能够成功化解危机的方案吗？",
        "hypothesis": "杠杆资金不能用。"
    },
    {
        "track": "pr",
        "id": 1375,
        "text": "老张在整理父亲遗物时翻到了那本泛黄的日记，却没有记起日记里夹着的那张黑白照片是在二十年前拍摄的。",
        "hypothesis": "日记里夹着的那张黑白照片不是在二十年前拍摄的。"
    },
    {
        "track": "pr",
        "id": 1376,
        "text": "我能感觉出那三匹马已经跑出了汗，因为我闻到一股股汗的气味儿。",
        "hypothesis": "那三匹马已经跑出了汗"
    },
    {
        "track": "pr",
        "id": 1377,
        "text": "他们认为，本·拉登在讲话中只是表示声援伊拉克人民，并未表示他支持萨达姆的领导。",
        "hypothesis": "本·拉登不支持萨达姆的领导。"
    },
    {
        "track": "pr",
        "id": 1378,
        "text": "她因误会朋友而道歉，心里仍自责自己当初为何那么冲动。",
        "hypothesis": "她当初不冲动。"
    },
    {
        "track": "pr",
        "id": 1379,
        "text": "独有一个人留了下来，那人名叫贝加密诺，能说会道，不曾和他当面谈过的人简直想象不出他那条舌头有多么灵巧。",
        "hypothesis": "他那条舌头不非常灵巧。"
    },
    {
        "track": "pr",
        "id": 1380,
        "text": "尽管面对海量的反证数据，那位固执的指挥官仍然坚信敌军的主力部队已经全部撤退到了北方的山谷之中。",
        "hypothesis": "敌军的主力部队没有全部撤退到北方的山谷之中。"
    },
    {
        "track": "pr",
        "id": 1381,
        "text": "许多民众盲信民间偏方能够根治绝症，从而放弃了正规的医学治疗。",
        "hypothesis": "民间偏方不能根治绝症。"
    },
    {
        "track": "pr",
        "id": 1382,
        "text": "会议上的沉默不代表大家已经达成了最终的一致意见，后续的讨论仍然需要继续深入进行。",
        "hypothesis": "大家已经达成了最终的一致意见。"
    },
    {
        "track": "pr",
        "id": 1383,
        "text": "这是1926年的春天，五年级的学生李云鹤就这样被学校开除了。然而，当时的李云鹤并不懂得开除便意味着失学。",
        "hypothesis": "开除便意味着失学。"
    },
    {
        "track": "pr",
        "id": 1384,
        "text": "她难过又生气，但她并不责怪小芳勾引了自己的丈夫，从事情发生起她就没觉得这是小芳的错。",
        "hypothesis": "小芳勾引了她的丈夫。"
    },
    {
        "track": "pr",
        "id": 1385,
        "text": "警方在接到报案后迅速出动，通过调取沿途监控录像核实嫌疑车辆在案发当晚曾经多次出现在市中心的关键路口。",
        "hypothesis": "嫌疑车辆在案发当晚没有多次出现在市中心的关键路口。"
    },
    {
        "track": "pr",
        "id": 1386,
        "text": "我相信，就因为这件事才使得他落得这样悲惨的结局。",
        "hypothesis": "就因为这件事才使得他落得这样悲惨的结局。"
    },
    {
        "track": "pr",
        "id": 1387,
        "text": "时至今日，嗜酒已经被广泛地认为是一种瘾症，一种多半由于遗传而来的病症，而非被世人指责的道德沦陷。",
        "hypothesis": "嗜酒是一种瘾症，一种多半由于遗传而来的病症。"
    },
    {
        "track": "pr",
        "id": 1388,
        "text": "记者在深入调查三个月后向公众曝光了这家大型化工企业长期向地下河流排放未经处理的有毒废水。",
        "hypothesis": "这家大型化工企业没有长期向地下河流排放未经处理的有毒废水。"
    },
    {
        "track": "pr",
        "id": 1389,
        "text": "你们不会晓得那寂寞的日子多么难过。",
        "hypothesis": "那寂寞的日子很难过。"
    },
    {
        "track": "pr",
        "id": 1390,
        "text": "事实并没有证明美国国内的纺织业正在受到中国出口的纺织品的损害。",
        "hypothesis": "美国国内的纺织业正在受到中国出口的纺织品的损害。"
    },
    {
        "track": "pr",
        "id": 1391,
        "text": "科学家们至今不清楚这种深海生物在极端高压环境下是如何维持细胞正常代谢的。",
        "hypothesis": "这种深海生物在极端高压环境下不能维持细胞正常代谢。"
    },
    {
        "track": "pr",
        "id": 1392,
        "text": "我们难以忘记，在纽约市访问意大利居民区的时候，一百多名男女老少，涌出来欢迎我们。",
        "hypothesis": "在纽约市访问意大利居民区的时候，没有一百多名男女老少涌出来欢迎我们。"
    },
    {
        "track": "pr",
        "id": 1393,
        "text": "布莱尔反驳说，他绝不承认自己在对伊情报问题上误导了英国公众。",
        "hypothesis": "布莱尔在对伊情报问题上误导了英国公众。"
    },
    {
        "track": "pr",
        "id": 1394,
        "text": "或许在某些场合，他会难得放松说些轻佻的话，但那绝不表示他将认同你有这样的表现。",
        "hypothesis": "他不会认同你有这样的表现。"
    },
    {
        "track": "pr",
        "id": 1395,
        "text": "官方如此，就怪不了市民抢水。恐慌激发的生存本能。",
        "hypothesis": "发生了市民抢水的事件。"
    },
    {
        "track": "pr",
        "id": 1396,
        "text": "使我终生难忘的是，在北方拉贾斯坦邦访问归途中，火车停在一个小站时，有个老农妇，居然将她做好的煎饼等着要送给我们。我真想象不到印度人民的情意是这么深厚，出现这么激动人心的情景！",
        "hypothesis": "印度人民的情意不非常深厚。"
    },
    {
        "track": "pr",
        "id": 1397,
        "text": "曼青低了头，暂时不响；对于夫人的爱护他的微意，他未始不感得一种甜味，但是不能承认夫人的思想和态度是正当。",
        "hypothesis": "夫人的思想和态度是正当。"
    },
    {
        "track": "pr",
        "id": 1398,
        "text": "面对这种毫无根据的指责和充满恶意的揣测，老实巴交的老张接受不了自己的清白名声被随意地践踏。",
        "hypothesis": "老张的清白名声没有被随意地践踏。"
    },
    {
        "track": "pr",
        "id": 1399,
        "text": "历史学者对照不同版本的史书与出土简牍，推断这场战役实际发生的时间比传统记载早了整整十年。",
        "hypothesis": "这场战役实际发生的时间比传统记载早了整整十年。"
    },
    {
        "track": "pr",
        "id": 1400,
        "text": "内海善雄说，几年前，有人曾认为，贫穷的非洲没有能力发展电信业。",
        "hypothesis": "贫穷的非洲没有能力发展电信业。"
    },
    {
        "track": "pr",
        "id": 1401,
        "text": "这位经验丰富的老中医在把脉时敏锐地察觉到病人的心脏跳动节奏出现了极不规律的异常变化。",
        "hypothesis": "病人的心脏跳动节奏出现了极不规律的异常变化。"
    },
    {
        "track": "pr",
        "id": 1402,
        "text": "我能感觉出那三匹马已经跑出了汗，因为我闻到一股股汗的气味儿。",
        "hypothesis": "那三匹马还没有跑出汗。"
    },
    {
        "track": "pr",
        "id": 1403,
        "text": "赵树理同志创作的最大特点：在全部叙述与描写时也运用了简练而丰富的群众语言。这些语言在描写群众的心理、行动，以至写景，同样被证明是很生动，很有魄力！",
        "hypothesis": "赵树理同志所运用的群众语言是很生动、很有魄力的。"
    },
    {
        "track": "pr",
        "id": 1404,
        "text": "所以方罗兰愈说她不了解，愈不肯承认自己也有半分的不是，方太太愈不肯让步。",
        "hypothesis": "方罗兰也有半分的不是。"
    },
    {
        "track": "pr",
        "id": 1405,
        "text": "他举起右手，发誓自己从未做过违背良心的事。",
        "hypothesis": "他曾做过违背良心的事。"
    },
    {
        "track": "pr",
        "id": 1406,
        "text": "刘益谦并不自认是个有眼光的收藏家，也没有意愿去学习具体的艺术知识，曾说过“我不懂什么艺术，我的优势是有资金”。",
        "hypothesis": "刘益谦不是个有眼光的收藏家。"
    },
    {
        "track": "pr",
        "id": 1407,
        "text": "消防队员在浓烟弥漫的废墟中反复搜寻，起初没有闻出那堆看似普通的灰烬下还埋藏着正在阴燃的电线。",
        "hypothesis": "那堆看似普通的灰烬下没有埋藏着正在阴燃的电线。"
    },
    {
        "track": "pr",
        "id": 1408,
        "text": "审计部门在审查完所有原始凭证后，核实这笔巨额支出完全符合公司规定的财务流程。",
        "hypothesis": "这笔巨额支出完全符合公司规定的财务流程。"
    },
    {
        "track": "pr",
        "id": 1409,
        "text": "巴沙尔则说，他乐观地相信，伊拉克会认真遵守联合国安理会决议并销毁其武器。",
        "hypothesis": "伊拉克不会认真遵守联合国安理会决议并销毁其武器。"
    },
    {
        "track": "pr",
        "id": 1410,
        "text": "我们十分欣赏地注意到，你们从来没有企图对我们施加压力，或要我们付出代价，你们一向是慷慨地、正直地、毫无偏见地考虑关系的实质，而不计较得失。",
        "hypothesis": "你们不曾对我们施加压力。"
    },
    {
        "track": "pr",
        "id": 1411,
        "text": "评论员在文章中暗指现任管理层的决策风格过于保守，完全无法适应当前瞬息万变的国际市场环境。",
        "hypothesis": "现任管理层的决策风格过于保守，完全无法适应当前瞬息万变的国际市场环境。"
    },
    {
        "track": "pr",
        "id": 1412,
        "text": "据服务员介绍，他们营业到凌晨1点左右，但并没有听到店外有任何异常动静。",
        "hypothesis": "店外没有异常动静。"
    },
    {
        "track": "pr",
        "id": 1413,
        "text": "经过多次核对，技术人员终于确认服务器集群在昨晚的维护窗口期间完成了所有补丁的自动安装。",
        "hypothesis": "服务器集群在昨晚的维护窗口期间没有完成所有补丁的自动安装。"
    },
    {
        "track": "pr",
        "id": 1414,
        "text": "他忘记自己已经关好了窗户，半夜突然下起了雨才想起来。",
        "hypothesis": "他还没有关好窗户。"
    },
    {
        "track": "pr",
        "id": 1415,
        "text": "我坚信知识是人类社会进步的阶梯，即使脸朝黄土背朝天又岂能辍学。",
        "hypothesis": "知识不是人类社会进步的阶梯。"
    },
    {
        "track": "pr",
        "id": 1416,
        "text": "说实在的，我来过中国很多次，走了很多地方，没有预料到珠海是个这么好的城市，珠海发展得这么快，建设得这么好，是我非常敬佩的。",
        "hypothesis": "珠海是个很好的城市。"
    },
    {
        "track": "pr",
        "id": 1417,
        "text": "我们宣布一切把德国牵入一个新战争、牵入侵略集团——包括欧洲委员会、北大西洋公约及舒曼计划——的义务和协定都是对德国人民的犯罪。所有这种义务和协定我们决不承认它是合法的。",
        "hypothesis": "这种义务和协定是合法的。"
    },
    {
        "track": "pr",
        "id": 1418,
        "text": "古代哲学家假想世界由水、火、土、气四种基本元素构成，并以此解释万物的生成与消亡。",
        "hypothesis": "世界不是由水、火、土、气四种基本元素构成。"
    },
    {
        "track": "pr",
        "id": 1419,
        "text": "戈尔在讲话中说：“我和克林顿总统真诚地相信，这项发明对这个国家很有益处。”",
        "hypothesis": "这项发明对这个国家很有益处。"
    },
    {
        "track": "pr",
        "id": 1420,
        "text": "他的样子是那么诚实，脸上是那么简单可爱，人们好象只好信任他，不敢想这个傻大个子是会敲人的。",
        "hypothesis": "这个傻大个子不是会敲人的。"
    },
    {
        "track": "pr",
        "id": 1421,
        "text": "台湾性教育协会理事长郑丞杰说，多数人认为自己是对方唯一的性伴侣，因此容易使自己身陷艾滋病的危险。",
        "hypothesis": "对于多数人来说，自己不是对方唯一的性伴侣。"
    },
    {
        "track": "pr",
        "id": 1422,
        "text": "治安听了，心里好舒服啊！长林不说咱前几年那些麻哈事，只说“没出世”！这话说得得体。治安从心里叹服长林真是个好老汉。",
        "hypothesis": "长林是个好老汉。"
    },
    {
        "track": "pr",
        "id": 1423,
        "text": "是啊，自由的人也许感觉不到自由是幸福，等到自由人做了奴隶的时候，那才知道自由的确是可贵的。",
        "hypothesis": "自由是幸福。"
    },
    {
        "track": "pr",
        "id": 1424,
        "text": "当服务器日志显示出异常的数据流量峰值时，网络安全工程师立刻意识到外部黑客已经成功突破了第一道防火墙。",
        "hypothesis": "外部黑客还没有成功突破第一道防火墙。"
    },
    {
        "track": "pr",
        "id": 1425,
        "text": "所有这些报纸都完全控制在各报业公司的主人手中，并遵照嘱咐将其文字运用当作舆论的表现，装作是表现人民感情、思想、愿望的喉舌。",
        "hypothesis": "所有这些报纸是表现人民感情、思想、愿望的喉舌。"
    },
    {
        "track": "pr",
        "id": 1426,
        "text": "在我们B组比赛中的4个失球全部来自定位球。我们必须注意到自己的失误,哪怕任意球是克罗地亚队的特长,也不代表着当时的我们没有过错。",
        "hypothesis": "当时的我们没有过错。"
    },
    {
        "track": "pr",
        "id": 1427,
        "text": "八圈完了，廉伯太太缓了一口气，可是不敢明说她不愿继续受罪。",
        "hypothesis": "廉伯太太愿意继续受罪。"
    },
    {
        "track": "pr",
        "id": 1428,
        "text": "但是有一天梁刚夫来，看见梅女士浸淫在书本里，又听到黄因明讲起“少奶奶”的笑话，便说单看书也不中用，说什么革命的斗争的宇宙观和人生观应该从实生活中去领受。",
        "hypothesis": "黄因明没有讲起“少奶奶”的笑话。"
    },
    {
        "track": "pr",
        "id": 1429,
        "text": "苏联专家非常注意礼貌，非常尊重我们教研室中的中国老教授。我们体会，这决不是什么形式问题。因为决不能设想一个没有礼貌的科学家是会谦虚地尊重别人的意见的。",
        "hypothesis": "一个没有礼貌的科学家是会谦虚地尊重别人的意见的。"
    },
    {
        "track": "pr",
        "id": 1430,
        "text": "此前，他在漫长的职业生涯中还没有遇到任何一个人在董事会议期间突然起身离席。",
        "hypothesis": "有人在董事会议期间突然起身离席。"
    },
    {
        "track": "pr",
        "id": 1431,
        "text": "但遗憾的是，生活中一些父母并没有认识到犯错是培养孩子认真的一个好时机。",
        "hypothesis": "犯错是培养孩子认真的一个好时机。"
    },
    {
        "track": "pr",
        "id": 1432,
        "text": "她在深夜反思时觉悟到自己对家人的忽视已经伤害了他们的感情，决定多花时间陪伴。",
        "hypothesis": "她对家人的忽视已经伤害了他们的感情。"
    },
    {
        "track": "pr",
        "id": 1433,
        "text": "她看到同事对她态度冷淡，疑心同事心里觉得她不够友好。",
        "hypothesis": "同事心里对她友好。"
    },
    {
        "track": "pr",
        "id": 1434,
        "text": "美国不受攻击的时代已经一去不复返了。低估苏联反击侵略的实际可能性，而夸大自己的可能性（特别是在战略弹道火箭方面），并不证明美国军事活动家是理智的。",
        "hypothesis": "美国军事活动家是理智的。"
    },
    {
        "track": "pr",
        "id": 1435,
        "text": "伦敦工人日报记者阿兰·魏宁顿九日自开城报道：李奇微勉强部分地同意了朝中方面为尽可能迅速地恢复谈判而提出的建议；这并没有证明美方已回心转意，而是证明了舆论的力量。",
        "hypothesis": "美方已回心转意。"
    },
    {
        "track": "pr",
        "id": 1436,
        "text": "政府和执政党人士指出，西欧没有单独同莫斯科谈判的基础。",
        "hypothesis": "西欧没有单独同莫斯科谈判的基础。"
    },
    {
        "track": "pr",
        "id": 1437,
        "text": "柬埔寨王国政府首相洪森1日表示，他欢迎红色高棉领导人乔森潘和农谢回归柬社会是为了促进国家统一和民族和解，但他并没有担保任何人免于被起诉。",
        "hypothesis": "任何人都可以免于被起诉。"
    },
    {
        "track": "pr",
        "id": 1438,
        "text": "她轻蔑地笑了笑，嘲讽他明明内心很脆弱，却总喜欢用强硬的外表来掩饰。",
        "hypothesis": "他内心不脆弱，也不总喜欢用强硬的外表来掩饰。"
    },
    {
        "track": "pr",
        "id": 1439,
        "text": "生物学家观察了这种罕见昆虫在特定温度下的产卵行为以及幼虫的孵化周期，推测出气候变化正在显著改变它们的繁殖模式。",
        "hypothesis": "气候变化正在显著改变这种昆虫的繁殖模式。"
    },
    {
        "track": "pr",
        "id": 1440,
        "text": "有些家长相信鼓励是唯一的方法，或是一味地严格要求。",
        "hypothesis": "鼓励是唯一的方法。"
    },
    {
        "track": "pr",
        "id": 1441,
        "text": "调查在朝鲜和中国的细菌战事实国际科学委员会”的委员们，在会到被俘中的美国空军战俘奎恩、伊纳克、奥尼尔、克尼斯之后，在他们报告书中写道：“委员会的委员们认为对这几个战俘并没有施用肉体和精神上的压力，强迫他们发表声明。他们发表声明，都是出于自愿的。",
        "hypothesis": "对这几个战俘施用了肉体和精神上的压力，强迫他们发表声明。"
    },
    {
        "track": "pr",
        "id": 1442,
        "text": "这只被困在玻璃瓶里的苍蝇妄想它只要不断撞击瓶底就能找到通往外面花园的出口。",
        "hypothesis": "那只苍蝇只要不断撞击瓶底就能找到通往外面花园的出口。"
    },
    {
        "track": "pr",
        "id": 1443,
        "text": "我听她的声名，比大隈伯还要大，我就不服她比千代子姐姐要好。",
        "hypothesis": "她比千代子姐姐要好。"
    },
    {
        "track": "pr",
        "id": 1444,
        "text": "不过，向我们进攻的敌人有七八万人，我也不敢担保我的军队是可靠的，因为军队会由于数量相差悬殊而发生动摇。",
        "hypothesis": "我的军队是不可靠的。"
    },
    {
        "track": "pr",
        "id": 1445,
        "text": "许多传统学者不能理解年轻一代将街头涂鸦视为一种高雅的艺术形式，认为那只是对公共财产的破坏。",
        "hypothesis": "年轻一代将街头涂鸦视为一种高雅的艺术形式。"
    },
    {
        "track": "pr",
        "id": 1446,
        "text": "她不曾意料到听到那首歌时自己的眼眶会突然湿润。",
        "hypothesis": "听到那首歌时她的眼眶没有突然湿润。"
    },
    {
        "track": "pr",
        "id": 1447,
        "text": "所以严格的来说，只要明白西门吹雪的为人，就不会认为他是个不懂礼貌的人。",
        "hypothesis": "他是个不懂礼貌的人。"
    },
    {
        "track": "pr",
        "id": 1448,
        "text": "丽莎·海恩斯则更加肯定地认为史蒂芬妮已成为麦当娜与的对手。",
        "hypothesis": "史蒂芬妮没有成为麦当娜的对手。"
    },
    {
        "track": "pr",
        "id": 1449,
        "text": "这些声音被假设是流星游离的活跃湍流与地球磁场的作用，引起的无线电脉冲。",
        "hypothesis": "这些声音是流星游离的活跃湍流与地球磁场的作用。"
    },
    {
        "track": "pr",
        "id": 1450,
        "text": "他不会怪天气不好，只是心里盼着能早点放晴。",
        "hypothesis": "天气不好。"
    },
    {
        "track": "pr",
        "id": 1451,
        "text": "眼下，有些人并不认同住房供应存在结构性过剩，而认为空置房增加是宏观调控政策所带来的负作用。",
        "hypothesis": "住房供应存在结构性过剩。"
    },
    {
        "track": "pr",
        "id": 1452,
        "text": "在审讯中，李相芝虽招认了杀害王德河的罪行，但司法科仍然主观地认为王、熊是杀人犯。",
        "hypothesis": "王、熊是杀人犯。"
    },
    {
        "track": "pr",
        "id": 1453,
        "text": "我们有些年青歌者，声音本质，得天独厚。但临到歌曲技巧上比较困难，特别是困难而又较快的段落，往往不够用功，仓促应阵，因而匆匆忙忙，上气不接下气。但是这些歌者，好像并没有认识到，这是一个不小的弱点。",
        "hypothesis": "这是一个很小的弱点。"
    },
    {
        "track": "pr",
        "id": 1454,
        "text": "母亲笑着摇摇头，嗔怪女儿总是这么调皮。",
        "hypothesis": "女儿不总是这么调皮。"
    },
    {
        "track": "pr",
        "id": 1455,
        "text": "村里的老人都觉着今年夏天的雨水比往年多了许多，河边的庄稼都被淹没了。",
        "hypothesis": "今年夏天的雨水比往年多了许多。"
    },
    {
        "track": "pr",
        "id": 1456,
        "text": "我们非常非常的谈得来，也彼此相互依赖对方，但一直以来我都没发觉我们相互爱着对方。",
        "hypothesis": "我们没有相互爱着对方。"
    },
    {
        "track": "pr",
        "id": 1457,
        "text": "她品尝着那熟悉的味道，记得第一次吃到时心里满是惊喜和满足。",
        "hypothesis": "她第一次吃到时心里满是惊喜和满足。"
    },
    {
        "track": "pr",
        "id": 1458,
        "text": "这次他决定不去。有许多的理由使他这样下了决心。其中的一个是父亲没有给他寄了钱来。他不愿承认这是个最重要的理由，可是他无法不去思索这点事儿。",
        "hypothesis": "父亲没有给他寄了钱来不是最重要的理由。"
    },
    {
        "track": "pr",
        "id": 1459,
        "text": "这位年轻的学者在发表那篇轰动学界的论文之前，自以为他提出的理论模型能够完美解释所有观测到的异常数据，却未曾料到后续的实验结果会彻底推翻他的核心假设。",
        "hypothesis": "这位年轻的学者提出的理论模型不能完美解释所有观测到的异常数据。"
    },
    {
        "track": "pr",
        "id": 1460,
        "text": "小窦笑道：“那是不经心在园里跌了一跤，头上没有觉得粘上了一大块青苔；你没有别的话，只好捉风捕影的血口喷人罢了。”",
        "hypothesis": "头上粘上了一大块青苔。"
    },
    {
        "track": "pr",
        "id": 1461,
        "text": "集市上哄传东头的那座石桥的桥墩发生了松动。",
        "hypothesis": "东头的那座石桥的桥墩没有发生松动。"
    },
    {
        "track": "pr",
        "id": 1462,
        "text": "我心明白，奥拉利亚，你在倾慕我。我知你痴心相印，笃信你钟情于我。仰慕春思尽表露，幸福美满无失落。",
        "hypothesis": "奥拉利亚钟情于我。"
    },
    {
        "track": "pr",
        "id": 1463,
        "text": "投资者认为国债投资可靠，比储蓄利率高等，因此就成为一种惯性购买行为。",
        "hypothesis": "国债投资可靠，比储蓄利率高等。"
    },
    {
        "track": "pr",
        "id": 1464,
        "text": "其实韩语中有近七成是汉字词，有很多词语和中文发音非常相似，然而这绝不代表韩语简单。",
        "hypothesis": "韩语不简单。"
    },
    {
        "track": "pr",
        "id": 1465,
        "text": "不知这少女何时爬到了梁上，竟然谁也没有知觉，虽说众人都是凝神注视东西两宗比剑，但总不能不知头顶上伏着一个人，这件事传将出去，“无量剑”的人可丢得大了。",
        "hypothesis": "“无量剑”众人的头顶上没有伏着一个人。"
    },
    {
        "track": "pr",
        "id": 1466,
        "text": "五岁的我并不认得站在照片墙中央穿着军装的男子就是牺牲在边疆的我的父亲。",
        "hypothesis": "站在照片墙中央穿着军装的男子就是牺牲在边疆的我的父亲。"
    },
    {
        "track": "pr",
        "id": 1467,
        "text": "她并不理解那些所谓的安慰反而令我更焦躁。",
        "hypothesis": "那些所谓的安慰没有令我更焦躁。"
    },
    {
        "track": "pr",
        "id": 1468,
        "text": "直到法庭出示了关键的监控录像证据，被告律师没有了解到他的当事人在案发当晚曾经独自返回过犯罪现场并取走了那把沾血的匕首。",
        "hypothesis": "他的当事人在案发当晚曾经独自返回过犯罪现场并取走了那把沾血的匕首。"
    },
    {
        "track": "pr",
        "id": 1469,
        "text": "她眼见孩子第一次学会走路，脸上露出了欣慰的笑容。",
        "hypothesis": "孩子第一次学会走路。"
    },
    {
        "track": "pr",
        "id": 1470,
        "text": "宋健也指出，中国的高技术还是落后的。因此，需要得到海外学者的支持。",
        "hypothesis": "中国的高技术还是落后的。"
    },
    {
        "track": "pr",
        "id": 1471,
        "text": "博物馆的资深修复专家仔细端详后，终于认得这幅残破画卷角落里的印章是宋代某位著名画家的私印。",
        "hypothesis": "这幅残破画卷角落里的印章不是宋代某位著名画家的私印。"
    },
    {
        "track": "pr",
        "id": 1472,
        "text": "他深悉敌军此次行动的目标是占领这座战略要地，因此提前做好了防御准备。",
        "hypothesis": "敌军此次行动的目标不是占领这座战略要地。"
    },
    {
        "track": "pr",
        "id": 1473,
        "text": "他常说，一个好的编辑，同时也应该是很好的学术研究的组织者和实际参加者，因为如果没有进行研究和写作的切身体验，就不会理解学术研究和从事著作是一种十分艰苦的劳动，因而也就不容易与作者建立起水乳交融的亲密关系。",
        "hypothesis": "学术研究和从事著作不是一种十分艰苦的劳动。"
    },
    {
        "track": "pr",
        "id": 1474,
        "text": "科学家利用高精度的激光干涉仪测定两颗中子星在合并瞬间释放出的引力波频率发生了剧烈变化。",
        "hypothesis": "两颗中子星在合并瞬间释放出的引力波频率发生了剧烈变化。"
    },
    {
        "track": "pr",
        "id": 1475,
        "text": "世界各国媒体在评论日本方案时，都指出，日本的建议带有政治动机。",
        "hypothesis": "日本的建议不带政治动机。"
    },
    {
        "track": "pr",
        "id": 1476,
        "text": "今年，她32岁，在她看来她早已过了小女生爱做梦的年龄，即使单身也不会幻想自己未来的那个他像“柳时镇”那样英俊潇洒。",
        "hypothesis": "她未来的那个他像“柳时镇”那样英俊潇洒。"
    },
    {
        "track": "pr",
        "id": 1477,
        "text": "\"太太！太太！\"他用给人留下深刻印象的声音高声说，\"这事与您无关！谁也不会指控您是教唆者和同谋者，何况罪证还是您发现的，是您把口袋翻了过来：可见您毫不知情。\"",
        "hypothesis": "您是教唆者和同谋者。"
    },
    {
        "track": "pr",
        "id": 1478,
        "text": "在回来后一月余的今天，我回想起在京时朋友们待我的盛情和所得的印象，都觉得还是如在目前。",
        "hypothesis": "我在京时朋友们不曾盛情相待。"
    },
    {
        "track": "pr",
        "id": 1479,
        "text": "许多古代的炼金术士都曾幻想普通的金属可以在特定的化学反应中瞬间转变成珍贵的黄金。",
        "hypothesis": "普通的金属在特定的化学反应中不能瞬间转变成珍贵的黄金。"
    },
    {
        "track": "pr",
        "id": 1480,
        "text": "赵耀东还哀叹工商业中公营事业更是长期不振，存在着“呆人”、“呆料”和“呆时”问题。",
        "hypothesis": "工商业中公营事业长期不振，存在“呆人”、“呆料”和“呆时”问题。"
    },
    {
        "track": "pr",
        "id": 1481,
        "text": "公司在制定下一季度预算时，考虑到原材料价格在过去三个月内上涨了百分之十五，适当削减了非核心项目的开支。",
        "hypothesis": "原材料价格在过去三个月内没有上涨百分之十五。"
    },
    {
        "track": "pr",
        "id": 1482,
        "text": "我们并没有认为希腊是一个小国，在中国人的心目中，希腊有古老的文明，希腊人民有很高的智慧。",
        "hypothesis": "希腊是一个小国。"
    },
    {
        "track": "pr",
        "id": 1483,
        "text": "评论指出，《真理报》的这些说法是对世界舆论的嘲弄。事实表明很难证明苏联是言行一致的。",
        "hypothesis": "苏联不是言行一致的。"
    },
    {
        "track": "pr",
        "id": 1484,
        "text": "绝大多数国家认为，决定对毗邻海域的国家权限，这是每个国家的主权。",
        "hypothesis": "决定对毗邻海域的国家权限不是每个国家的主权。"
    },
    {
        "track": "pr",
        "id": 1485,
        "text": "廉伯太太缓了一口气，可是不敢明说她不愿继续受罪。",
        "hypothesis": "她不愿继续受罪。"
    },
    {
        "track": "pr",
        "id": 1486,
        "text": "这位资深评论员在专栏文章中声称这种新兴的艺术形式缺乏深度，完全无法与传统经典相提并论。",
        "hypothesis": "这种新兴的艺术形式不缺乏深度，能够与传统经典相提并论。"
    },
    {
        "track": "pr",
        "id": 1487,
        "text": "他有血有肉、有情有义、有爱有恨、有得有失、有功有过、有生有死，因此他不是也不可能是所谓的完人，但这并不能否认他绝对是一个伟人，是一个大写的人。",
        "hypothesis": "他绝对是一个伟人，是一个大写的人。"
    },
    {
        "track": "pr",
        "id": 1488,
        "text": "这几天确实是有些发烧，但我并不以为创造力会因此衰退。",
        "hypothesis": "我的创造力会因发烧而衰退。"
    },
    {
        "track": "pr",
        "id": 1489,
        "text": "经过对过去三十年气象记录的详尽分析，气象学家计算出该地区夏季平均降雨量比上个世纪增加了百分之十五。",
        "hypothesis": "该地区夏季平均降雨量没有比上个世纪增加百分之十五。"
    },
    {
        "track": "pr",
        "id": 1490,
        "text": "有的家长可能会感到很委屈：现在都是独生子女，竞争这么激烈，不包办一切、让孩子一门心思学习行么？我绝不怀疑中国家长对孩子的爱与责任感不够，相反我认为是过了头，变成了一种过度保护，而且方式也不对。",
        "hypothesis": "中国家长对孩子的爱与责任感足够。"
    },
    {
        "track": "pr",
        "id": 1491,
        "text": "不信，请把他的画与历代的佳作比一比，你不会发现他是谁的门徒——他的画中有了新的血脉，前无古人。同时，你又不能指出他的画不是纯粹的中国画——他把新的成分带手儿取来，控制在他自己的笔下，不许它们喧宾夺主啊。",
        "hypothesis": "他的画不是纯粹的中国画。"
    },
    {
        "track": "pr",
        "id": 1492,
        "text": "母亲厌憎邻居家的孩子对小动物施暴的举动，觉得这种残忍的天性令人不寒而栗。",
        "hypothesis": "邻居家的孩子不曾对小动物施暴。"
    },
    {
        "track": "pr",
        "id": 1493,
        "text": "不去看看，都不能感受到那湖光山色是何等美如仙境！",
        "hypothesis": "那湖光山色美如仙境。"
    },
    {
        "track": "pr",
        "id": 1494,
        "text": "最后一次，阎伪集结了五六十人，大车五辆及民夫进犯抢粮，这时刚巧碰到村里三支枪被借走了两支，情况万分紧张，国瑾乃带一个小组拿上那唯一的一支枪去打麻雀阵，迷惑敌人；玉小带一组拿着喇叭筒向敌人呐喊：“冲锋！前进！”并接近敌人投手榴弹，敌人不摸虚实，以为正规军赶到，遂狼狈逃窜。",
        "hypothesis": "村里三支枪被借走了两支。"
    },
    {
        "track": "pr",
        "id": 1495,
        "text": "她并没有说她已经是那守猎人的情人，她只说她喜欢他。",
        "hypothesis": "她已经是那守猎人的情人。"
    },
    {
        "track": "pr",
        "id": 1496,
        "text": "她并没有料到自己会对尤金感觉兴趣。",
        "hypothesis": "她对尤金不感觉兴趣。"
    },
    {
        "track": "pr",
        "id": 1497,
        "text": "那些生活在偏远山区的古老部落至今仍然迷信每逢月圆之夜山神会走出洞穴巡视领地。",
        "hypothesis": "每逢月圆之夜没有山神走出洞穴巡视领地。"
    },
    {
        "track": "pr",
        "id": 1498,
        "text": "然而，对于某些患者群体和特定临床背景而言，其他“不正常”的窦性心律才是正常的。因此“正常窦性心律”也被考虑为术语的滥用。",
        "hypothesis": "“正常窦性心律”是术语的滥用。"
    },
    {
        "track": "pr",
        "id": 1499,
        "text": "尽量不要打搅他，他有时候也需要独处的快乐，那并不证明他不爱你。",
        "hypothesis": "他爱你。"
    },
    {
        "track": "pr",
        "id": 1500,
        "text": "作为一名新型高速歼击机的试飞员，滑俊深知自己理论基础差，必须比别人下更大的苦功学习。",
        "hypothesis": "滑俊的理论基础比较差。"
    },
    {
        "track": "pr",
        "id": 1501,
        "text": "他文质彬彬，同记者谈话戏称“以文会友”，使你无法想到他曾经是一位将军。",
        "hypothesis": "他曾经是一位将军。"
    },
    {
        "track": "pr",
        "id": 1502,
        "text": "他无奈地自嘲自己是个彻头彻尾的傻瓜，竟然相信了那种荒谬的谎言。",
        "hypothesis": "他是个彻头彻尾的傻瓜。"
    },
    {
        "track": "pr",
        "id": 1503,
        "text": "只是看到他们的一些毛病，没注意他们的长处，而消极地限制他们毛病的发展，没有认识到工人是很干脆的，比较容易发动，说干就干，说动员起来就起来，",
        "hypothesis": "工人是很干脆的。"
    },
    {
        "track": "pr",
        "id": 1504,
        "text": "可是中国人民并不如胡适和曾琦所想象那样容易受欺骗，他们很清楚苏联为了要迅速与德、奥签订和约曾提出许多具体建议。",
        "hypothesis": "苏联为了要迅速与德、奥签订和约曾提出许多具体建议。"
    },
    {
        "track": "pr",
        "id": 1505,
        "text": "吉丹森在回答记者提出的是否知道黄向伊拉克出口通信设备时表示：“我无法相信这些指控是准确的。我感到非常迷惑。”但美国官方强调，黄在出口这些通信设备时知道最终目的地。",
        "hypothesis": "这些指控是不准确的。"
    },
    {
        "track": "pr",
        "id": 1506,
        "text": "当然喽，我不敢自称已经是陶瓷学权威了，但是那天整整一个晚上，加上整整一夜（除了中间的短暂休息），以及第二天整整一个上午，我确实是在勤学强记大批的名词儿。",
        "hypothesis": "我不是陶瓷学权威。"
    },
    {
        "track": "pr",
        "id": 1507,
        "text": "先让宋上大放下厚厚的棉布帘子，又让马西平东塞一下西堵一下，屋里立马就暗淡下来，只能看见地上放着两只日军的钢盔。",
        "hypothesis": "地上放着两只日军的钢盔。"
    },
    {
        "track": "pr",
        "id": 1508,
        "text": "他们认为朝鲜战争可以轻易地结束。",
        "hypothesis": "朝鲜战争可以轻易地结束。"
    },
    {
        "track": "pr",
        "id": 1509,
        "text": "气象学家结合卫星云图与地面监测数据，估测出台风登陆时的中心风力将达到十二级以上。",
        "hypothesis": "台风登陆时的中心风力不会达到十二级以上。"
    },
    {
        "track": "pr",
        "id": 1510,
        "text": "但他并不懂跪拜是礼节，只当做玩耍，所以在跌跤时还格格地笑着。",
        "hypothesis": "跪拜是礼节。"
    },
    {
        "track": "pr",
        "id": 1511,
        "text": "和日常生活的对话不同，在日常生活当中，当我们听别人说的话时，我们不会默认别人说的是对的，相反，我们会评估对方的论证的合理性。",
        "hypothesis": "别人说的是对的。"
    },
    {
        "track": "pr",
        "id": 1512,
        "text": "研一时学习索伯列夫空间，我曾在某个下午为了同一个问题连续去请教陈老师三次，陈老师并不嫌我愚笨钻牛角尖，而是给我耐心讲解，直到我彻底懂了为止。",
        "hypothesis": "我愚笨钻牛角尖。"
    },
    {
        "track": "pr",
        "id": 1513,
        "text": "她并不理解那些所谓的安慰反而令我更焦躁。",
        "hypothesis": "那些所谓的安慰反而令我更焦躁。"
    },
    {
        "track": "pr",
        "id": 1514,
        "text": "然而，在听证会上，嫌疑犯的辩护律师再次提出理由否认DNA鉴定：第一，概率标准在英国没有法定标准，不能以概率来作为定罪的证据。第二，两个血样的DNA并非完全匹配；第三，DNA鉴定只鉴定DNA片断，难以证明两种DNA完全匹配。陪审团以证据不足，宣判嫌疑犯无罪。",
        "hypothesis": "两种DNA完全匹配。"
    },
    {
        "track": "pr",
        "id": 1515,
        "text": "绝大多数国家坚定地认为，决定对毗邻海域的国家权限，这是每个国家的主权。",
        "hypothesis": "决定对毗邻海域的国家权限是每个国家的主权。"
    },
    {
        "track": "pr",
        "id": 1516,
        "text": "市委注意了“抓两头”，笼统地认为这些中间状态的单位问题不大。",
        "hypothesis": "这些中间状态的单位问题不小。"
    },
    {
        "track": "pr",
        "id": 1517,
        "text": "媒体记者深入调查后曝光这家工厂的生产流程极不人道，完全无视工人的基本尊严。",
        "hypothesis": "这家工厂的生产流程很人道，完全尊重工人的基本尊严。"
    },
    {
        "track": "pr",
        "id": 1518,
        "text": "这些天，北京市民出行并没有感到交通过于拥堵，反而发现交通违章处理速度在加快。",
        "hypothesis": "交通非常拥堵。"
    },
    {
        "track": "pr",
        "id": 1519,
        "text": "孩子没有立即回答老师的问题，不意味着他完全不知道这道数学题的解题思路。",
        "hypothesis": "他完全不知道这道数学题的解题思路。"
    },
    {
        "track": "pr",
        "id": 1520,
        "text": "业内人士指出，钟玲的出现无疑是为中国艺术体操注入了一针强心剂，她也逐渐被认同为中国艺术体操的未来之星。",
        "hypothesis": "钟玲是中国艺术体操的未来之星。"
    },
    {
        "track": "pr",
        "id": 1521,
        "text": "使我感到惊讶的是，我们承认有一个最好的朋友这一事实竟然可以被理解成我们是这个朋友的卫星国。",
        "hypothesis": "我们不是这个朋友的卫星国。"
    },
    {
        "track": "pr",
        "id": 1522,
        "text": "老战士在回忆录中坦白他在那场战役的关键时刻曾因为恐惧而暂时离开了自己的战斗岗位。",
        "hypothesis": "他在那场战役的关键时刻没有因为恐惧而暂时离开自己的战斗岗位。"
    },
    {
        "track": "pr",
        "id": 1523,
        "text": "要“放下架子”，以真正平等的态度对待干部和群众，使人感到人们互相间的关系确实是平等的，而不要使人感到你是“上司”，你是“官”。特别是对待工农群众，不能嫌他们说话罗嗦。",
        "hypothesis": "他们说话不罗嗦。"
    },
    {
        "track": "pr",
        "id": 1524,
        "text": "尽管警方已经封锁了现场并提取了大量指纹证据，但发言人没透露嫌疑人是通过窗户潜入这间密室的。",
        "hypothesis": "嫌疑人不是通过窗户潜入这间密室的。"
    },
    {
        "track": "pr",
        "id": 1525,
        "text": "那个时代，国家虽糟，也不至如此之甚。家境虽不好，也比如今强得多。我虽不算个少爷，可也不能说是穷小子。",
        "hypothesis": "我是穷小子。"
    },
    {
        "track": "pr",
        "id": 1526,
        "text": "老教授责怪自己的助手操作仪器不稳。",
        "hypothesis": "老教授的助手操作仪器很稳。"
    },
    {
        "track": "pr",
        "id": 1527,
        "text": "如果女方不是在第一次见面就问：你有没有房子可以结婚？那么，可以说，她和你在一起喜欢的是你的人，而不是你的房子。因为她是先认可了你的人之后，到了结婚时才考虑房子的问题。所以，我并不能认同想要买一套房子结婚的女人都是拜金的。",
        "hypothesis": "想要买一套房子结婚的女人不都是拜金的。"
    },
    {
        "track": "pr",
        "id": 1528,
        "text": "她没有预备买东西，但仍然想进去瞧一瞧。",
        "hypothesis": "她想买东西。"
    },
    {
        "track": "pr",
        "id": 1529,
        "text": "在长达数小时的审讯之后，他终于承认在深夜潜入了博物馆并窃走了那幅珍贵的油画。",
        "hypothesis": "他在深夜潜入了博物馆并窃走了那幅珍贵的油画。"
    },
    {
        "track": "pr",
        "id": 1530,
        "text": "有的私方人员工作很积极，每天都很晚才回家，但是得到的不是鼓励，而是被怀疑别有用意。",
        "hypothesis": "有的私方人员工作很积极，每天都很晚才回家，不是别有用意。"
    },
    {
        "track": "pr",
        "id": 1531,
        "text": "不，我不相信自己竟然藏着这么感性的一面，现在的我根本就不是我了。",
        "hypothesis": "我藏着非常感性的一面。"
    },
    {
        "track": "pr",
        "id": 1532,
        "text": "《医院管理学》重点是讲在现有条件下，如何科学地管理好县以上综合医院，并对逐步建成具有我国特点的现代化医院作了初步探索。辽宁省卫生局拟于近期内对《医院管理学》初稿进行修改定稿，正式公开发行。",
        "hypothesis": "辽宁省卫生局近期内对《医院管理学》初稿进行修改定稿。"
    },
    {
        "track": "pr",
        "id": 1533,
        "text": "农民一方面珍惜辛勤劳动得来的成果，不遇到大的自然灾害和生、老、病、死等，认为参加保险不划算，是“把钱扔到了水里”，意识不到参加保险是分散和转移自身风险的一种好形式。",
        "hypothesis": "参加保险是分散和转移自身风险的一种好形式。"
    },
    {
        "track": "pr",
        "id": 1534,
        "text": "培根的唯物论虽然还带有神学的不彻底性，但是这并不足以掩盖他的唯物论的精神实质，他的唯物论虽然已经有了当时正在形成发展的机械唯物论的萌芽，但是还不就是机械唯物论。他没有企图把物质看成死板的东西，把物质运动归结为简单的机械运动。",
        "hypothesis": "培根把物质看成是死板的东西，把物质运动归结为简单的机械运动。"
    },
    {
        "track": "pr",
        "id": 1535,
        "text": "今年五月，工人们组织篮球队要和外面球队比赛，当时他们向我们借运动衣，我们认为这是只发给代表队的，就没借给他们。",
        "hypothesis": "运动衣不是发给代表队的。"
    },
    {
        "track": "pr",
        "id": 1536,
        "text": "直到法庭出示了关键的监控录像证据，被告律师没有了解到他的当事人在案发当晚曾经独自返回过犯罪现场并取走了那把沾血的匕首。",
        "hypothesis": "他的当事人在案发当晚没有独自返回犯罪现场并取走那把沾血的匕首。"
    },
    {
        "track": "pr",
        "id": 1537,
        "text": "邻居们私下里嫌弃那栋新盖的别墅风格太俗气，金色的栏杆配着红色的砖墙，完全破坏了整条街道的雅致氛围。",
        "hypothesis": "那栋新盖的别墅风格太俗气。"
    },
    {
        "track": "pr",
        "id": 1538,
        "text": "也有人根据对刘兰芝的才能、服饰的夸张描写，而认为她是汉朝一般富贵人家的女子。",
        "hypothesis": "她不是汉朝一般富贵人家的女子。"
    },
    {
        "track": "pr",
        "id": 1539,
        "text": "全国政协常委、北京市第四中学校长刘长铭就坚定表示，农村孩子是人力资源富矿，农村孩子某些方面的能力要超过城市孩子，如独立性、直接生活经验等，这些是一个人原始创造力的来源。而对于出生于农村的孩子，根据“大数据”臆想农村孩子过着悲惨的童年，更是令人无语。事实上，农村孩子在广阔的大自然中成长，物质条件虽然相对艰苦，但幸福感不一定比城市孩子弱，与大自然的亲近让他们有着丰富的童年生活。",
        "hypothesis": "农村孩子过着悲惨的童年。"
    },
    {
        "track": "pr",
        "id": 1540,
        "text": "仁民的声音依旧很低，但又是很坚定的，这表示他的头脑还很清楚，他的意志还很坚决。",
        "hypothesis": "他的头脑不清楚，他的意志不坚决。"
    },
    {
        "track": "pr",
        "id": 1541,
        "text": "他们没有亲身在旧中国那种环境中生活过，也许已很难想象当年中华民族的悲惨境遇，也很难体会到改变这种境遇多么艰难。",
        "hypothesis": "改变这种境遇并没有非常艰难。"
    },
    {
        "track": "pr",
        "id": 1542,
        "text": "老侦探仔细分析了现场留下的每一个细微线索，猜测凶手是一个心思极其缜密且对受害者怀有深刻怨恨的人。",
        "hypothesis": "凶手是一个心思极其缜密且对受害者怀有深刻怨恨的人。"
    },
    {
        "track": "pr",
        "id": 1543,
        "text": "整个董事会的成员在听完这份冗长且充满专业术语的报告后，大多面面相觑，显然都没明白财务总监提出的那项激进重组方案究竟是如何导致公司现金流瞬间断裂的。",
        "hypothesis": "财务总监提出的那项激进重组方案导致了公司现金流瞬间断裂。"
    },
    {
        "track": "pr",
        "id": 1544,
        "text": "尽管飞行员在驾驶舱内，但依然感到飞机的起落架已经接触到了跑道表面并产生摩擦。",
        "hypothesis": "飞机的起落架已经接触到了跑道表面并产生摩擦。"
    },
    {
        "track": "pr",
        "id": 1545,
        "text": "财报公布后，大家开始怀疑这家公司的盈利模式根本就是在欺骗股东。",
        "hypothesis": "这家公司的盈利模式根本就是在欺骗股东。"
    },
    {
        "track": "pr",
        "id": 1546,
        "text": "他高兴妈妈还活着，但一时还不能懂为什么她住在美占领区，却天天到苏区去工作。",
        "hypothesis": "他妈妈不住在美占领区，也不天天到苏区去工作。"
    },
    {
        "track": "pr",
        "id": 1547,
        "text": "媒体记者深入调查后曝光这家工厂的生产流程极不人道，完全无视工人的基本尊严。",
        "hypothesis": "这家工厂的生产流程极不人道，完全无视工人的基本尊严。"
    },
    {
        "track": "pr",
        "id": 1548,
        "text": "他不明白我心底的防线早就已经崩塌了。",
        "hypothesis": "我心底的防线早就已经崩塌了。"
    },
    {
        "track": "pr",
        "id": 1549,
        "text": "上次来的时候，他曾经对她吐出那样的渴望，用那样热烈的词句描摹出他的爱慕，所以尽管离别和都市生活的刺激暂时冲淡了对她的忆念，她还是深信，他依然是爱她的。",
        "hypothesis": "他不再爱她了。"
    },
    {
        "track": "pr",
        "id": 1550,
        "text": "里面有人走近门前，他以为张嫂来开门了。谁知却是接生婆抱着新生的婴儿在门缝里传出话来：“恭喜大少爷，是一位公子。”她说完就转身走开了。觉新还听到她一面拍着婴儿，一面自言自语：“可惜生下来就没有娘了。”",
        "hypothesis": "接生婆一面拍着婴儿，一面自言自语。"
    },
    {
        "track": "pr",
        "id": 1551,
        "text": "他现在名满文坛，可是还忘不掉小时候没好好进过学校，老觉得那些“正途出身”的人瞧不起自己，随时随地提防人家损伤自己的尊严。",
        "hypothesis": "小时候没好好进过学校。"
    },
    {
        "track": "pr",
        "id": 1552,
        "text": "她难过又生气，但她并不责怪小芳勾引了自己的丈夫，从事情发生起她就没觉得这是小芳的错。",
        "hypothesis": "小芳没有勾引她的丈夫。"
    },
    {
        "track": "pr",
        "id": 1553,
        "text": "世界各国媒体在评论日本方案时，都不约而同地指出，日本的建议带有政治动机。",
        "hypothesis": "日本的建议不带政治动机。"
    },
    {
        "track": "pr",
        "id": 1554,
        "text": "常人难以想象眼前这条穿越地势崎岖的金刚山区的铁路是仅用了14个月就建成通车的。",
        "hypothesis": "眼前这条穿越地势崎岖的金刚山区的铁路不是仅用了14个月就建成通车的。"
    },
    {
        "track": "pr",
        "id": 1555,
        "text": "半英里以外的敌人不会不知道我们正在前来。",
        "hypothesis": "我们正在前来。"
    },
    {
        "track": "pr",
        "id": 1556,
        "text": "这些高管在过去几个月内涉嫌利用内幕信息提前买卖股票。",
        "hypothesis": "这些高管在过去几个月内没有利用内幕信息提前买卖股票。"
    },
    {
        "track": "pr",
        "id": 1557,
        "text": "据路透社讯，日本的报纸认为吉田的新内阁是不稳固的。",
        "hypothesis": "吉田的新内阁是不稳固的。"
    },
    {
        "track": "pr",
        "id": 1558,
        "text": "我们并没有认为希腊是一个小国，在中国人的心目中，希腊有古老的文明，希腊人民有很高的智慧。",
        "hypothesis": "希腊不是一个小国。"
    },
    {
        "track": "pr",
        "id": 1559,
        "text": "那些缺乏实地调研的评论家常常妄言这种传统的耕作方式极其落后，完全不符合现代农业的发展潮流。",
        "hypothesis": "这种传统的耕作方式极其落后，完全不符合现代农业的发展潮流。"
    },
    {
        "track": "pr",
        "id": 1560,
        "text": "综合分析两类材料，判定寇准生活豪侈，应该说较为接近历史的真实，较为稳妥一些；退一步讲，也不至得出“廉洁俭朴”的结论吧！我们作借古讽今之文，跟写学术论文一样，也要有科学性，对于古人事迹必须深思慎取，而不能想当然。",
        "hypothesis": "寇准生活豪侈。"
    },
    {
        "track": "pr",
        "id": 1561,
        "text": "同学们总是嘲笑他穿着过时，认为他的审美还停留在上个世纪。",
        "hypothesis": "他穿着过时。"
    },
    {
        "track": "pr",
        "id": 1562,
        "text": "他没预料到比赛失败后自己会这般沮丧。",
        "hypothesis": "比赛失败后他不沮丧。"
    },
    {
        "track": "pr",
        "id": 1563,
        "text": "梅尔·吉布森的政治观点偏保守派，虽然他并未承认自己是共和党支持者，但被有些人形容有「保守」和「右倾」的倾向。",
        "hypothesis": "梅尔·吉布森不是共和党支持者。"
    },
    {
        "track": "pr",
        "id": 1564,
        "text": "如果把这些地方的苹果、梨移到广东，特别是移到海拔和纬度又较低的地方，由于冬季的低温不足以打破它们的休眠，是不能奢望它们生长正常的。",
        "hypothesis": "苹果、梨在广东，特别是海拔和纬度较低的地方生长正常。"
    },
    {
        "track": "pr",
        "id": 1565,
        "text": "森森姜林不想见到通江的孩子误入歧途，也不想见到通江的家庭因为教育失衡导致破裂。",
        "hypothesis": "通江的家庭已经因为教育失衡导致破裂。"
    },
    {
        "track": "pr",
        "id": 1566,
        "text": "她虽然视若不见地走开了，却不知晓自己已然动了恻隐之心。",
        "hypothesis": "她已然动了恻隐之心。"
    },
    {
        "track": "pr",
        "id": 1567,
        "text": "你不晓得我心里很难受。我不是青年，我没有青春。",
        "hypothesis": "我心里很难受。"
    },
    {
        "track": "pr",
        "id": 1568,
        "text": "克莱·萧尔克莱·拉维恩·萧尔，为美国路易斯安那州新奥尔良的一位商人。他是唯一一个被起诉与肯尼迪遇刺有关，但被无罪释放的人。",
        "hypothesis": "克莱·萧尔克莱·拉维恩·萧尔与肯尼迪遇刺有关。"
    },
    {
        "track": "pr",
        "id": 1569,
        "text": "许多写信的人正当地指出了迟迟收到报纸这令人难以忍受的事实。",
        "hypothesis": "许多写信的人迟迟收到报纸。"
    },
    {
        "track": "pr",
        "id": 1570,
        "text": "年迈的祖母常常拉着我的手，说她不会忘记年轻时那段岁月十分艰难，全家人靠着野菜和树皮才熬过了冬天。",
        "hypothesis": "年轻时那段岁月不十分艰难。"
    },
    {
        "track": "pr",
        "id": 1571,
        "text": "我美丽的宝，你老换名字，我都差点忘记你是火锅侠了。",
        "hypothesis": "你不是火锅侠。"
    },
    {
        "track": "pr",
        "id": 1572,
        "text": "这只被人工饲养长大的老虎不懂得野外猎物在草丛中移动时会刻意压低身体以避开视线。",
        "hypothesis": "野外猎物在草丛中移动时不会刻意压低身体以避开视线。"
    },
    {
        "track": "pr",
        "id": 1573,
        "text": "假如我不曾在城科，我想我永远也不会看见城科的天空是有多么的美丽。",
        "hypothesis": "城科的天空非常美丽。"
    },
    {
        "track": "pr",
        "id": 1574,
        "text": "清晨，住在山脚下的老猎人听见远处的山谷里传来一阵沉闷的雷声，紧接着暴雨便倾盆而下。",
        "hypothesis": "远处的山谷里传来一阵沉闷的雷声。"
    },
    {
        "track": "pr",
        "id": 1575,
        "text": "我真的很难忘记馒头店店主哭泣的画面。",
        "hypothesis": "馒头店店主未曾在哭泣。"
    },
    {
        "track": "pr",
        "id": 1576,
        "text": "喜出望外的梅里恩以十分肯定的语气说：“经过四部剧作的对比，无法证明它们的作者不是同一个人；莎士比亚确实写了《托马斯·莫尔爵士的书籍》这部剧本。”",
        "hypothesis": "四部剧作的作者不是同一个人。"
    },
    {
        "track": "pr",
        "id": 1577,
        "text": "丽莎·海恩斯则认为史蒂芬妮已成为麦当娜与的对手。",
        "hypothesis": "史蒂芬妮已成为麦当娜与的对手。"
    },
    {
        "track": "pr",
        "id": 1578,
        "text": "投资者认为国债投资可靠，比储蓄利率高等，因此就成为一种惯性购买行为。",
        "hypothesis": "国债投资不可靠，不比储蓄利率高等。"
    },
    {
        "track": "pr",
        "id": 1579,
        "text": "使我终生难忘的是，在北方拉贾斯坦邦访问归途中，火车停在一个小站时，有个老农妇，居然将她做好的煎饼等着要送给我们。我真想象不到印度人民的情意是这么深厚，出现这么激动人心的情景！",
        "hypothesis": "印度人民的情意非常深厚。"
    },
    {
        "track": "pr",
        "id": 1580,
        "text": "对内虽然我们对当前的政治不满意，但我们不能否认当局所努力的方向是对的。",
        "hypothesis": "当局所努力的方向是对的。"
    },
    {
        "track": "pr",
        "id": 1581,
        "text": "习惯了传统教学模式的老年教师反感学校强制要求他们在所有课程中完全取消黑板板书。",
        "hypothesis": "学校没有强制要求老年教师在所有课程中完全取消黑板板书。"
    },
    {
        "track": "pr",
        "id": 1582,
        "text": "清晨第一缕阳光洒进山谷时，早起的村民见到成群的候鸟正从湿地起飞向南迁徙。",
        "hypothesis": "成群的候鸟正从湿地起飞向南迁徙。"
    },
    {
        "track": "pr",
        "id": 1583,
        "text": "经验丰富的老刑警盯着监控录像看了三遍，依然没看出嫌疑人是如何在进入电梯前更换了鞋子的。",
        "hypothesis": "嫌疑人在进入电梯前没有更换鞋子。"
    },
    {
        "track": "pr",
        "id": 1584,
        "text": "就像向南，虽然后面还是和杨晓云在一起了，可是我们并不能否认他对遥遥还是有感情的。",
        "hypothesis": "向南对遥遥没有感情。"
    },
    {
        "track": "pr",
        "id": 1585,
        "text": "表面上他愈装得和蔼愉悦，内心里愈是感到忧惧沉重。他确信姞拉并不知道保罗在芝加哥，而保罗正在搞的事既不道德又不保险。",
        "hypothesis": "保罗不在芝加哥。"
    },
    {
        "track": "pr",
        "id": 1586,
        "text": "以“有计划商品经济”来限定社会主义的经济本质，虽然在确立商品经济在社会主义经济中的地位时具有石破天惊的意义，但是既不能证实资本主义经济就是“无计划的商品经济”，也不能说明非社会主义经济是“有计划的自然经济”。",
        "hypothesis": "资本主义经济就是“无计划的商品经济”。"
    },
    {
        "track": "pr",
        "id": 1587,
        "text": "不过，老板终究是智慧的，他并没有指责李嘉诚“羽毛丰满，不记栽培器重之恩”，而是约李嘉诚到酒楼，设宴为他辞工饯行，这令李嘉诚十分感动。",
        "hypothesis": "李嘉诚羽毛丰满，不记栽培器重之恩。"
    },
    {
        "track": "pr",
        "id": 1588,
        "text": "声明说，希腊人民绝不承认这次大选是合法的。",
        "hypothesis": "这次大选是合法的。"
    },
    {
        "track": "pr",
        "id": 1589,
        "text": "反正翻来覆去，强词夺理，全是他的话。我从前并不知道他这样油嘴。这次同回国算领教了。",
        "hypothesis": "他非常油嘴。"
    },
    {
        "track": "pr",
        "id": 1590,
        "text": "赵君武笑得很开朗，道：“我刚才差点想一头撞死，可是现在却只想再活几年，活得越长越好。",
        "hypothesis": "赵君武没有一头撞死。"
    },
    {
        "track": "pr",
        "id": 1591,
        "text": "与它们的幻龙类近亲相比，鸥龙较为原始，拥有短的颈部与小的鳍状肢。它们被推测游泳能力较差，有大部分时间在干燥陆地上，或在浅水中猎食。",
        "hypothesis": "鸥龙游泳能力较强。"
    },
    {
        "track": "pr",
        "id": 1592,
        "text": "作为一个革命者，不能幻想革命的道路是“一帆风顺”的。我们应当既能顺风而行，也能逆风而进。",
        "hypothesis": "革命的道路不是“一帆风顺”的。"
    },
    {
        "track": "pr",
        "id": 1593,
        "text": "他完成这项艰巨任务后，感到无比的自豪和满足。",
        "hypothesis": "他无比自豪和满足。"
    },
    {
        "track": "pr",
        "id": 1594,
        "text": "苏格拉底诚然是在雅典民主派当权期间被处死的，但这并不能证明他站在贵族派一边。",
        "hypothesis": "苏格拉底没有站在贵族派一边。"
    },
    {
        "track": "pr",
        "id": 1595,
        "text": "今年2月，同样在密苏里州，强生刚刚被判决需要向另一名女性的家人支付7200万美元赔偿金。该名女子已因罹患卵巢癌而去世，而她的去世被认为与其持续使用强生的婴儿爽身粉和沐浴露有关。",
        "hypothesis": "强生需要向另一名女性的家人支付7200万美元赔偿金。"
    },
    {
        "track": "pr",
        "id": 1596,
        "text": "直到目前为止，西方国家没有表示愿意实事求是地研究这些建设性的建议。",
        "hypothesis": "西方国家愿意实事求是地研究这些建设性的建议。"
    },
    {
        "track": "pr",
        "id": 1597,
        "text": "虽然教练对队员们的体能训练提出了极高要求，但他不期待这群年轻选手能在明天的决赛中击败经验丰富的卫冕冠军。",
        "hypothesis": "这群年轻选手能在明天的决赛中击败经验丰富的卫冕冠军。"
    },
    {
        "track": "pr",
        "id": 1598,
        "text": "海德公园很冷清，也没有遇见政治家在那里发表演说。",
        "hypothesis": "政治家在那里发表演说。"
    },
    {
        "track": "pr",
        "id": 1599,
        "text": "劳埃德表示，英国并不喜欢有比较多的国家参加最高级会议。",
        "hypothesis": "没有比较多的国家参加了最高级会议。"
    },
    {
        "track": "pr",
        "id": 1600,
        "text": "据说，比弗拉里小23岁的范斯不能认同爱瑟儿与一个老得可以做爸爸的男人结婚，并抱怨弗拉里的唱歌和跳舞技巧大不如从前。",
        "hypothesis": "爱瑟儿与一个老得可以做爸爸的男人结婚。"
    },
    {
        "track": "pr",
        "id": 1601,
        "text": "这本畅销书不仅让殡葬业成了时髦话题，还使非盈利殡葬业组织从1.7万家激增至近百万家。这种现象被形容为“米特福德效应”，她的书被谴责为一场“红色阴谋”。它改变了一个行业，还影响了总统的葬礼。",
        "hypothesis": "她的书不是一场“红色阴谋”。"
    },
    {
        "track": "pr",
        "id": 1602,
        "text": "失去孩子的母亲怨恨那个醉酒的司机在深夜超速行驶撞倒了正在过马路的行人，随后却驾车逃离了事故现场。",
        "hypothesis": "那个醉酒的司机没有在深夜超速行驶撞倒正在过马路的行人，也没有驾车逃离事故现场。"
    },
    {
        "track": "pr",
        "id": 1603,
        "text": "他总结了国际上有关背痛的科研成果后认为，凭科学数据还无法证明背痛与长久坐姿行为有关。",
        "hypothesis": "背痛与长久坐姿行为无关。"
    },
    {
        "track": "pr",
        "id": 1604,
        "text": "我们不能断言说这些工作完全没有意义，因为像一切研究工作一样，其意义在哪里一时是看不清、说不清的，也许将来某一个时候会发现它们的作用。",
        "hypothesis": "这些工作有意义。"
    },
    {
        "track": "pr",
        "id": 1605,
        "text": "肉呢？肉看甚么了？牛和猪我倒可以吃，羊肉我可不大行。羊肉最鲜，你怎么不爱吃？我总嫌它有膻味儿。",
        "hypothesis": "它有膻味儿。"
    },
    {
        "track": "pr",
        "id": 1606,
        "text": "面对即将到来的台风，经验丰富的船长不担心船只偏离既定的航线。",
        "hypothesis": "船只偏离了既定的航线。"
    },
    {
        "track": "pr",
        "id": 1607,
        "text": "他听后发出震耳欲聋的大笑，我无法忘记他当时坐在沙发里缩成一团时的愉快情景。",
        "hypothesis": "他当时没有坐在沙发里缩成一团。"
    },
    {
        "track": "pr",
        "id": 1608,
        "text": "国际社会在多次会议后最终决定不谴责那个内陆国家因干旱而暂时关闭边境。",
        "hypothesis": "那个内陆国家因干旱而暂时关闭边境。"
    },
    {
        "track": "pr",
        "id": 1609,
        "text": "做好事为啥大家还不买账？在上级党组织的引领下，谢兰与社区党委班子认真分析原因：一方面，社区开发早，居民想着能靠拆迁获得一大笔补偿；另一方面，也有居民担心政府这么做是面子工程。",
        "hypothesis": "政府这么做是面子工程。"
    },
    {
        "track": "pr",
        "id": 1610,
        "text": "东北农业生产力之所以获得如此迅速的恢复与发展，绝不能设想仅是由于实行土地改革的结果。",
        "hypothesis": "东北农业生产力之所以获得如此迅速的恢复与发展仅是由于实行土地改革的结果。"
    },
    {
        "track": "pr",
        "id": 1611,
        "text": "八十年代的青年们再也不愿意相信某些官僚主义者自居为党的化身了，再也不愿意相信“大锅饭”算是社会主义的优越性了。",
        "hypothesis": "那些官僚主义者是党的化身。"
    },
    {
        "track": "pr",
        "id": 1612,
        "text": "在金库设计时，原来并未考虑允许人们进来参观。但金库建成后，国内外银行界的同行纷纷要求参观，遂决定开设这一“旅游”项目，让世界各国银行界的同行进一步了解美国和美元。",
        "hypothesis": "金库原来不允许人们进来参观。"
    },
    {
        "track": "pr",
        "id": 1613,
        "text": "她静下心来后终于认识到自己其实一直害怕孤独。",
        "hypothesis": "她一直不害怕孤独。"
    },
    {
        "track": "pr",
        "id": 1614,
        "text": "坐在驾驶座上的司机当时正专注于观察前方的野鹿，没瞧见那辆超速行驶的黑色轿车正在急速靠近。",
        "hypothesis": "那辆超速行驶的黑色轿车没有在急速靠近。"
    },
    {
        "track": "pr",
        "id": 1615,
        "text": "火星上有植物生长的可能性，还不能证明火星上有植物存在。这如同水里可以养鱼，并不能证明水里就有鱼是同样的道理。",
        "hypothesis": "火星上有植物存在。"
    },
    {
        "track": "pr",
        "id": 1616,
        "text": "他走在路上，不知心中为何会莫名地感到焦虑不安。",
        "hypothesis": "他的心中莫名地感到焦虑不安。"
    },
    {
        "track": "pr",
        "id": 1617,
        "text": "不信，请把他的画与历代的佳作比一比，你不会发现他是谁的门徒——他的画中有了新的血脉，前无古人。同时，你又不能指出他的画不是纯粹的中国画——他把新的成分带手儿取来，控制在他自己的笔下，不许它们喧宾夺主啊。",
        "hypothesis": "他的画是纯粹的中国画。"
    },
    {
        "track": "pr",
        "id": 1618,
        "text": "他默默点头，知道自己内心其实很期待这次旅行。",
        "hypothesis": "他自己内心其实很期待这次旅行。"
    },
    {
        "track": "pr",
        "id": 1619,
        "text": "校内和校外的同志们都认为这篇论文是成功的，对实际工作有指导意义。",
        "hypothesis": "这篇论文是成功的，对实际工作有指导意义。"
    },
    {
        "track": "pr",
        "id": 1620,
        "text": "我并不怀疑确实有个女人进了你房间。",
        "hypothesis": "没有女人进了你房间。"
    },
    {
        "track": "pr",
        "id": 1621,
        "text": "谢玉树因为二人站在走廊上，免不得有来来往往的人注意，便拉着卫璧安的手，站在课堂后一座假山石边，看看身后无人，然后笑道：“你还害臊吗？你这人太不长进了。”卫璧安不肯承认害臊，就把刚才同学开玩笑的事，说了一遍。",
        "hypothesis": "卫璧安感到害臊。"
    },
    {
        "track": "pr",
        "id": 1622,
        "text": "眼下，有些人并不认同住房供应存在结构性过剩，而认为空置房增加是宏观调控政策所带来的负作用。",
        "hypothesis": "住房供应不存在结构性过剩。"
    },
    {
        "track": "pr",
        "id": 1623,
        "text": "这份由双方律师共同起草的文件代表两家公司完成了资产合并并确立了新的董事会架构。",
        "hypothesis": "两家公司没有完成资产合并并确立新的董事会架构。"
    },
    {
        "track": "pr",
        "id": 1624,
        "text": "第二天，窗上刚麻麻亮，杨效忠醒来，披好衣服出门，就看见海明领着社员出发了。",
        "hypothesis": "海明领着社员出发了。"
    },
    {
        "track": "pr",
        "id": 1625,
        "text": "由于一个粒子是不可分裂的，我们也不能认定它同时穿过了两个小孔。",
        "hypothesis": "一个粒子同时穿过了两个小孔。"
    },
    {
        "track": "pr",
        "id": 1626,
        "text": "但由于她随丈夫已经在许多国家工作过，所以并没有感到在日本的日子不好过。",
        "hypothesis": "在日本的日子不好过。"
    },
    {
        "track": "pr",
        "id": 1627,
        "text": "他诧异碑上看不见一个字，却又像有千千万万个字。",
        "hypothesis": "碑上看不见一个字。"
    },
    {
        "track": "pr",
        "id": 1628,
        "text": "当地居民通过长期的观察记录，不认同这条河流的水质在过去十年中没有任何变化。",
        "hypothesis": "这条河流的水质在过去十年中没有任何变化。"
    },
    {
        "track": "pr",
        "id": 1629,
        "text": "唯有你们二人，没怪我所托非人。",
        "hypothesis": "我所托非人。"
    },
    {
        "track": "pr",
        "id": 1630,
        "text": "作为一名资深的调香师，她在走进实验室的瞬间就闻出新合成的样品中混入了微量的硫化物杂质。",
        "hypothesis": "新合成的样品中没有混入微量的硫化物杂质。"
    },
    {
        "track": "pr",
        "id": 1631,
        "text": "校内和校外的同志们都认为这篇论文是成功的，对实际工作有指导意义。",
        "hypothesis": "这篇论文是失败的，对实际工作没有指导意义。"
    },
    {
        "track": "pr",
        "id": 1632,
        "text": "除了巫师、长老以外，芒戈传统信仰里还有一种宗教职业人员——先知，他们被相信能够操纵神灵力量，并凭此能力帮助和伤害人们。",
        "hypothesis": "先知能够操纵神灵力量，并凭此能力帮助和伤害人们。"
    },
    {
        "track": "pr",
        "id": 1633,
        "text": "他们谁也没有料到水是这样的珍贵。",
        "hypothesis": "水很珍贵。"
    },
    {
        "track": "pr",
        "id": 1634,
        "text": "劳埃德表示，英国并不喜欢有比较多的国家参加最高级会议。",
        "hypothesis": "有比较多的国家参加了最高级会议。"
    },
    {
        "track": "pr",
        "id": 1635,
        "text": "随着岁月的流逝，年幼的孩子不会记得父亲在离家的那个清晨悄悄把仅有的干粮塞进了他的书包。",
        "hypothesis": "父亲在离家的那个清晨悄悄把仅有的干粮塞进了他的书包。"
    },
    {
        "track": "pr",
        "id": 1636,
        "text": "老师明白学生上课走神是因为昨晚没休息好。",
        "hypothesis": "学生上课走神不是因为昨晚没休息好。"
    },
    {
        "track": "pr",
        "id": 1637,
        "text": "雨翔惊叹他会说“绰绰有余”这个成语。",
        "hypothesis": "他不会说“绰绰有余”这个成语。"
    },
    {
        "track": "pr",
        "id": 1638,
        "text": "爱因斯坦曾指出：物理学的前途在于建立统一场论。",
        "hypothesis": "物理学的前途在于建立统一场论。"
    },
    {
        "track": "pr",
        "id": 1639,
        "text": "谈话的时候，苏珊觉得尤金总是一个十分快乐的人。她看不出来他的欣快的外表里有着多么深切的渴望。",
        "hypothesis": "他的欣快的外表里有着非常深切的渴望。"
    },
    {
        "track": "pr",
        "id": 1640,
        "text": "社论最后说，“美国已经使全世界怀疑它的和平愿望，因为它今天高呼和平，而明天又扬言要扩大战争。人们必然不会相信美国真心诚意地希望越南和平。”",
        "hypothesis": "美国不是真心诚意地希望越南和平。"
    },
    {
        "track": "pr",
        "id": 1641,
        "text": "11月11日，马鞍山一处过街天桥上，一名市民斥责暴徒堵路破坏，被暴徒淋浇易燃液体点燃烧至重伤。",
        "hypothesis": "暴徒没有在过街天桥上堵路破坏。"
    },
    {
        "track": "pr",
        "id": 1642,
        "text": "干了26年铁路警察的谭凌云说，在过去半年约30万公里的执勤中，他已经没有碰到刑事案件甚至是严重的治安案件，恶性案件已经很多年没有发生了，现在他最多的事情是帮着乘客找手机和找行李。倒回10年前，他怎么也不会料到，铁路能变得这样安宁。",
        "hypothesis": "铁路不能变得这样安宁。"
    },
    {
        "track": "pr",
        "id": 1643,
        "text": "作家并非为了得奖而写作，获奖固然可喜，但并不能证明你就是最好的作家。",
        "hypothesis": "你就是最好的作家。"
    },
    {
        "track": "pr",
        "id": 1644,
        "text": "法国《国际邮报》的文章强烈抨击个别法国媒体报道疫情时使用歧视性词汇，强调对病毒传播的警惕不应等同于对亚裔的歧视。",
        "hypothesis": "个别法国媒体报道疫情时使用歧视性词汇。"
    },
    {
        "track": "pr",
        "id": 1645,
        "text": "我恼忿于他并未征求我的同意就要画我，但他微笑——无法否认他的微笑有迷人之处。",
        "hypothesis": "他的微笑没有迷人之处。"
    },
    {
        "track": "pr",
        "id": 1646,
        "text": "他从未嫌弃过她穿着朴素，反而觉得她自然大方。",
        "hypothesis": "她穿着朴素。"
    },
    {
        "track": "pr",
        "id": 1647,
        "text": "许多不在这个球状闪电领域工作的科学家是不能体会到球状闪电的领域特性是多么广泛的。",
        "hypothesis": "球状闪电的领域特性不是非常广泛的。"
    },
    {
        "track": "pr",
        "id": 1648,
        "text": "他到处吹嘘自己生了个儿子，好像那是什么了不得的事情一样。",
        "hypothesis": "他生了个儿子。"
    },
    {
        "track": "pr",
        "id": 1649,
        "text": "去年8月，这名身穿黑袍、头戴面罩，只露出双眼和鼻尖的持刀刽子手出现在美国人质史蒂文·索特洛夫被斩首的视频中。之后，他还被指认出现在杀害英国人质大卫·海恩斯、艾伦·亨宁，美国人质阿普杜· 拉赫曼·卡斯格以及上个月日本人质汤川遥菜和后藤健二的视频中。",
        "hypothesis": "这名持刀刽子手出现在杀害英国人质大卫·海恩斯、艾伦·亨宁，美国人质阿普杜· 拉赫曼·卡斯格以及上个月日本人质汤川遥菜和后藤健二的视频中。"
    },
    {
        "track": "pr",
        "id": 1650,
        "text": "在放映前，我们原本并未准备有意识地去宣传这部影片，组织更多的群众去看。",
        "hypothesis": "我们有意识地去宣传了这部影片。"
    },
    {
        "track": "pr",
        "id": 1651,
        "text": "当时有人怀疑他向文汇报写的稿子内容是否也有问题，但并没有指责他不该向党外报纸投稿。",
        "hypothesis": "他应该向党外报纸投稿。"
    },
    {
        "track": "pr",
        "id": 1652,
        "text": "找到店家理论时，对方一口咬定鲁维蓄意欺诈，甚至是口出恶言，侮辱鲁维的人格。“像我这样，不仅商品质量不过关影响工作进度，还被污蔑蓄意欺诈，算不算精神损害呢？严重的精神损害赔偿又怎么去界定呢？”",
        "hypothesis": "鲁维的行为是蓄意欺诈。"
    },
    {
        "track": "pr",
        "id": 1653,
        "text": "又听说父亲的处境狼狈，她就一厢情愿地认为她有责任拯救父亲于水火之中。",
        "hypothesis": "她没有责任拯救父亲于水火之中。"
    },
    {
        "track": "pr",
        "id": 1654,
        "text": "决议既不谴责印度是侵略者也不保证克什米尔人民行使自决权。",
        "hypothesis": "印度是侵略者。"
    },
    {
        "track": "pr",
        "id": 1655,
        "text": "他站在窗前望着远处连绵的乌云，没有料到一场突如其来的暴雨在几分钟内彻底淹没了整个低洼的街区。",
        "hypothesis": "一场突如其来的暴雨在几分钟内彻底淹没了整个低洼的街区。"
    },
    {
        "track": "pr",
        "id": 1656,
        "text": "尽管医生动用了最先进的影像设备进行全面扫描，他们依然没有查出病人的肺部深处隐藏着一块微小的塑料碎片。",
        "hypothesis": "病人的肺部深处没有隐藏着一块微小的塑料碎片。"
    },
    {
        "track": "pr",
        "id": 1657,
        "text": "但男孩幼小的心灵并不能懂得，妈妈是大人，她需要自己承担她的责任和情绪。",
        "hypothesis": "妈妈是大人，需要自己承担她的责任和情绪。"
    },
    {
        "track": "pr",
        "id": 1658,
        "text": "他们认为朝鲜战争可以轻易地结束。",
        "hypothesis": "朝鲜战争不可以轻易地结束。"
    },
    {
        "track": "pr",
        "id": 1659,
        "text": "因为只有做旧诗的人敢说不看新诗，做新诗的人从不肯说不懂旧诗的。",
        "hypothesis": "做新诗的人不懂旧诗。"
    },
    {
        "track": "pr",
        "id": 1660,
        "text": "她轻蔑地笑了笑，嘲讽他明明内心很脆弱，却总喜欢用强硬的外表来掩饰。",
        "hypothesis": "他内心很脆弱，却总喜欢用强硬的外表来掩饰。"
    },
    {
        "track": "pr",
        "id": 1661,
        "text": "面对邻居反复强调的那只流浪猫已经连续三天在车库角落产下幼崽的事实，老张始终没有相信那只瘦弱的母猫真的完成了分娩过程。",
        "hypothesis": "那只瘦弱的母猫没有完成分娩过程。"
    },
    {
        "track": "pr",
        "id": 1662,
        "text": "因为经济方面的原因，鲁迅购置古籍大抵是通行之本、易得之书，但这绝不表明他不重视版本，恰恰相反，他是很讲究版本的。",
        "hypothesis": "鲁迅不重视版本。"
    },
    {
        "track": "pr",
        "id": 1663,
        "text": "人们一直猜测那些小的暗晕应该和我们熟悉的超大暗晕内部结构不一样，但令人惊叹的是我们发现所有质量的暗晕竟然均具有极为相似的内部结构——中心致密，往外逐渐稀疏。",
        "hypothesis": "那些小的暗晕应该和我们熟悉的超大暗晕内部结构一样。"
    },
    {
        "track": "pr",
        "id": 1664,
        "text": "医生担心患者体内残留的微小血栓会随血液流动堵塞脑部血管，引发不可逆转的中风症状。",
        "hypothesis": "患者体内残留的微小血栓不会随血液流动堵塞脑部血管。"
    },
    {
        "track": "pr",
        "id": 1665,
        "text": "我虽然不愿说这是个有效的方法，可是也不能不承认这种预备的工夫足以使作者对故事的全体能准确的把握住，不至于把力量全用在开首，而后半落了空。",
        "hypothesis": "这是个有效的方法。"
    },
    {
        "track": "pr",
        "id": 1666,
        "text": "初雪把广阔无垠的大地一律拉平，花园也好，荒村也罢，全都失去了各自的特色，到处美丽得耀眼炫目，使人不能想象这个世界上竟会有几分钟之前发生的那种荒诞的丑剧，不能想象人会有那种龌龊得对自己也没有什么好处的心地。",
        "hypothesis": "人有那种龌龊得对自己也没有什么好处的心地。"
    },
    {
        "track": "pr",
        "id": 1667,
        "text": "第九集节目中，李威从3-0领先到最终被逆转而3-4失败的结果在网络上放出后，网友臆测李威有放水的嫌疑。",
        "hypothesis": "李威没有放水的嫌疑。"
    },
    {
        "track": "pr",
        "id": 1668,
        "text": "国王在战后发布的诏书中写道，为了安抚民心并重建国家秩序，王室不责怪普通百姓在围城期间为了保全家人性命而向敌军提供少量粮食。",
        "hypothesis": "普通百姓在围城期间为了保全家人性命而向敌军提供少量粮食。"
    },
    {
        "track": "pr",
        "id": 1669,
        "text": "他怕高又怕水，因而常被取笑是胆小鬼。",
        "hypothesis": "他是胆小鬼。"
    },
    {
        "track": "pr",
        "id": 1670,
        "text": "另据悉尼消息，“悉尼先锋晨报”在五月七日抨击哈利逊说，很难说哈利逊的态度具有“迅速谋求解决的诚意”。",
        "hypothesis": "哈利逊的态度不具有“迅速谋求解决的诚意”。"
    },
    {
        "track": "pr",
        "id": 1671,
        "text": "三蝶儿把眼圈一红，赶著背过脸儿去，假意去整理头发。",
        "hypothesis": "三蝶儿整理头发。"
    },
    {
        "track": "pr",
        "id": 1672,
        "text": "最使她高兴的是瑞宣回来，听到她的报告，并没有责备她轻举妄动。他笑了笑，只说了声：“救人总是好事！”",
        "hypothesis": "她没有轻举妄动。"
    },
    {
        "track": "pr",
        "id": 1673,
        "text": "这份解密的历史档案揭示当年那场外交谈判中双方代表曾秘密交换过三份补充备忘录。",
        "hypothesis": "当年那场外交谈判中双方代表曾秘密交换过三份补充备忘录。"
    },
    {
        "track": "pr",
        "id": 1674,
        "text": "我绝不认为自己是不认真学习的学生，然而就是在小学，我关心的也不是课堂上的学习，而是一些课外的事。",
        "hypothesis": "我是认真学习的学生。"
    },
    {
        "track": "pr",
        "id": 1675,
        "text": "总的来说，齐格菲防线的宣传意义几乎和它的战略意义一样大，在相当长的时间里，它都被宣称为一条坚固的防线，一直影响到了1944年，但到了真的面对它的时候，无论是德国人还是盟军，都发现这条防线的大部分设计已经不符合当时的战场形势了，尽管它起到了阻滞盟军的作用，但显然不像德国人声称的那样坚不可摧。",
        "hypothesis": "齐格菲防线在相当长的时间里不是一条坚固的防线。"
    },
    {
        "track": "pr",
        "id": 1676,
        "text": "所以方罗兰愈说她不了解，愈不肯承认自己也有半分的不是，方太太愈不肯让步。",
        "hypothesis": "方罗兰没有半分的不是。"
    },
    {
        "track": "pr",
        "id": 1677,
        "text": "但有不少父亲不认同自己已拥有和孩子建立亲子关系的权利。",
        "hypothesis": "自己已拥有和孩子建立亲子关系的权利。"
    },
    {
        "track": "pr",
        "id": 1678,
        "text": "尽管外面的雨下得非常大，正在赶路的邮递员不介意雨水打湿了他的制服，依旧坚持挨家挨户投递信件。",
        "hypothesis": "雨水打湿了他的制服。"
    },
    {
        "track": "pr",
        "id": 1679,
        "text": "怀恨在心的小张诬陷邻居在家里吸食毒品。",
        "hypothesis": "邻居在家里吸食毒品。"
    },
    {
        "track": "pr",
        "id": 1680,
        "text": "发现最近有很多假的负面消息在微博上转载，提醒大家别被一些别有用心的叛国者利用了，非我族类其心必异，绝不相信他们是好心肠！",
        "hypothesis": "那些别有用心的叛国者不是好心肠。"
    },
    {
        "track": "pr",
        "id": 1681,
        "text": "母亲的皱纹更深的刻在脸上了，叔父的胡子更乱的蔓延在脸上了，弟弟们拖着鼻涕和衣服的缺襟，露着大的眼珠和瘦削的两颊。一瞥中我留意到这灯正是从前在柿场上用的煤油灯，添上的是一条熏黑通弯铁丝，和玻璃瓶上的两条裂缝。",
        "hypothesis": "这灯是从前在柿场上用的煤油灯。"
    },
    {
        "track": "pr",
        "id": 1682,
        "text": "她不愿说他在做戏，他是诗班指挥，他是基督徒，他是文教授的儿子，她不能这么说他。",
        "hypothesis": "他没有在做戏。"
    },
    {
        "track": "pr",
        "id": 1683,
        "text": "但开会后回去只是层层布置，却没有很好检查，盲目地认为合同的执行没有问题，使得各级干部的片面“恩赐”观点没有及时纠正，收布时没有认真掌握质量，以致到时货物不能及时集中，质量够不上合同的规定。",
        "hypothesis": "合同的执行有问题。"
    },
    {
        "track": "pr",
        "id": 1684,
        "text": "我们不准备单纯地相信金字塔就是法老们的坟墓，围绕金字塔巧合的数据太多太多，然而，这真是一种巧合吗？",
        "hypothesis": "金字塔不是法老们的坟墓。"
    },
    {
        "track": "pr",
        "id": 1685,
        "text": "从以上试验结果可以肯定地指出，粪便经沼气发酵后可以基本达到无害化。",
        "hypothesis": "粪便经沼气发酵后可以基本达到无害化。"
    },
    {
        "track": "pr",
        "id": 1686,
        "text": "被告人否认在事故发生当晚曾驾驶那辆黑色轿车出现在市中心路段。",
        "hypothesis": "被告人在事故发生当晚没有驾驶那辆黑色轿车出现在市中心路段。"
    },
    {
        "track": "pr",
        "id": 1687,
        "text": "建立长跪在养父的灵前，他怎么也接受不了养父已经不在了。",
        "hypothesis": "他的养父还在。"
    },
    {
        "track": "pr",
        "id": 1688,
        "text": "他望着远方的天空，感觉心中充满了对未来的憧憬和期待。",
        "hypothesis": "他心中充满了对未来的憧憬和期待。"
    },
    {
        "track": "pr",
        "id": 1689,
        "text": "各地示威群众同仇敌忾，万众一心，纷纷表示绝不容忍兄弟邻邦受到侵犯。",
        "hypothesis": "兄弟邻邦没有受到侵犯。"
    },
    {
        "track": "pr",
        "id": 1690,
        "text": "市委注意了“抓两头”，认为这些中间状态的单位问题不大。",
        "hypothesis": "这些中间状态的单位问题不大。"
    },
    {
        "track": "pr",
        "id": 1691,
        "text": "大多数城镇居民并不接受本地文化掺入过多的外地文化，或者说过多外地人聚居。",
        "hypothesis": "本地文化掺入了过多的外地文化。"
    },
    {
        "track": "pr",
        "id": 1692,
        "text": "1998年苏哈托下台后，其总统一职由科技部长优素福·哈比比接任。此后苏哈托被揭发曾透过不同手段来为自己的家族及亲信致富，当中包括贪污、垄断等手段。",
        "hypothesis": "苏哈托曾透过不同手段来为自己的家族及亲信致富，当中包括贪污、垄断等手段。"
    },
    {
        "track": "pr",
        "id": 1693,
        "text": "也有人根据对刘兰芝的才能、服饰的夸张描写，而认为她是汉朝一般富贵人家的女子。",
        "hypothesis": "她是汉朝一般富贵人家的女子。"
    },
    {
        "track": "pr",
        "id": 1694,
        "text": "在我们国家已经能生产成套的矿山设备的今天，青年人是很难理解解放前我国矿山完全受制于外国人的情况的。",
        "hypothesis": "解放前我国矿山完全受制于外国人。"
    },
    {
        "track": "pr",
        "id": 1695,
        "text": "历史学家在查阅了新解密的档案馆卷宗后，确证这位被误解的将军在战争末期曾秘密策划过和平谈判。",
        "hypothesis": "这位被误解的将军在战争末期没有秘密策划过和平谈判。"
    },
    {
        "track": "pr",
        "id": 1696,
        "text": "他听后发出震耳欲聋的大笑，我无法忘记他当时坐在沙发里缩成一团时的愉快情景。",
        "hypothesis": "他当时坐在沙发里缩成一团。"
    },
    {
        "track": "pr",
        "id": 1697,
        "text": "春凤一听我讲婚姻法，就两眼望着我，凝神地听。我母亲起初不爱听，可是久而久之，她也有点爱听了，就是还不愿意说自己过去不对。",
        "hypothesis": "母亲过去不对。"
    },
    {
        "track": "pr",
        "id": 1698,
        "text": "单凭这专业架势，你肯定猜不出这位20岁出头的小伙子只是一位即将本科毕业的大四学生。",
        "hypothesis": "这位20岁出头的小伙子是一位即将本科毕业的大四学生。"
    },
    {
        "track": "pr",
        "id": 1699,
        "text": "法院既不充分相信基层工会的申诉，又不作任何调查，便简单地认为这个案件只是一般民事案件，不予受理。",
        "hypothesis": "这个案件只是一般民事案件。"
    },
    {
        "track": "pr",
        "id": 1700,
        "text": "许多资深经济学家在详细分析了该国的财政赤字数据后，不认同政府提出的通过大规模印钞来刺激短期经济增长的方案会导致恶性通货膨胀。",
        "hypothesis": "政府提出的通过大规模印钞来刺激短期经济增长的方案不会导致恶性通货膨胀。"
    },
    {
        "track": "pr",
        "id": 1701,
        "text": "他绝不相信西门吹雪就是杀死张英风的凶手，更不相信西门吹雪会和那些太监们同流合污。",
        "hypothesis": "西门吹雪不是杀死张英风的凶手。"
    },
    {
        "track": "pr",
        "id": 1702,
        "text": "我不会幻想真的被人理解，因为我不要与人平等。",
        "hypothesis": "我真的被人理解了。"
    },
    {
        "track": "pr",
        "id": 1703,
        "text": "许多沉迷于网络游戏的青少年自以为虚拟世界里的成就比现实生活中的努力更有价值。",
        "hypothesis": "虚拟世界里的成就并不比现实生活中的努力更有价值。"
    },
    {
        "track": "pr",
        "id": 1704,
        "text": "谁也不会料到那是一对鼻孔。",
        "hypothesis": "那是一对鼻孔。"
    },
    {
        "track": "pr",
        "id": 1705,
        "text": "但是，她从来没说她也爱他，尽管她确实说了“我也爱你。但可能不是同一种爱，但我确实爱你。”这仍然不能表明瑞秋曾经爱过甘瑟。",
        "hypothesis": "瑞秋不曾爱过甘瑟。"
    },
    {
        "track": "pr",
        "id": 1706,
        "text": "火灾现场的指挥官眼见得火势顺着风向迅速蔓延，吞噬了相邻的木屋，浓烟滚滚直冲云霄。",
        "hypothesis": "火势顺着风向迅速蔓延，吞噬了相邻的木屋，浓烟滚滚直冲云霄。"
    },
    {
        "track": "pr",
        "id": 1707,
        "text": "直到乡长张盈田、乡干部张世宽、区公安员刘念乡、区委书记张成栋、村妇联主任及当事人张学善、杨氏，以及当地群众证实了汤志高干涉婚姻自由的违法行为以后，汤才被迫承认在此案的处理上有错误。",
        "hypothesis": "汤志高在此案的处理上没有错误。"
    },
    {
        "track": "pr",
        "id": 1708,
        "text": "批评一个人的美丑，不能只看一部而忽略全体。我虽然说老张的鼻子象鸣蝉，嘴似烧饼，然而决不敢说他不好看。从他全体看来，你越看他嘴似烧饼，便越觉得非有鸣蝉式的鼻子配着不可。",
        "hypothesis": "老张好看。"
    },
    {
        "track": "pr",
        "id": 1709,
        "text": "晚会现场非常热闹，演员的表演真挚、精彩，我能感觉出他们是在用真心为医护人员表演。",
        "hypothesis": "演员们是在用真心为医护人员表演。"
    },
    {
        "track": "pr",
        "id": 1710,
        "text": "杜鲁门的弟弟是一位农夫，但是，母亲并没有认为这位做农夫的儿子是无能的。对她来说，每个孩子都令她感到自豪，无论儿子是总统还是农夫。",
        "hypothesis": "这位做农夫的儿子不是无能的。"
    },
    {
        "track": "pr",
        "id": 1711,
        "text": "老张在整理父亲遗物时翻到了那本泛黄的日记，却没有记起日记里夹着的那张黑白照片是在二十年前拍摄的。",
        "hypothesis": "日记里夹着的那张黑白照片是在二十年前拍摄的。"
    },
    {
        "track": "pr",
        "id": 1712,
        "text": "她品尝着那熟悉的味道，记得第一次吃到时心里满是惊喜和满足。",
        "hypothesis": "她第一次吃到时心里没有满是惊喜和满足。"
    },
    {
        "track": "pr",
        "id": 1713,
        "text": "卡秋莎暗暗爱上了他，却不敢向他表白，连自己都不敢承认产生了这种感情。",
        "hypothesis": "卡秋莎产生了这种感情。"
    },
    {
        "track": "pr",
        "id": 1714,
        "text": "医生结合病人多年的家族病史和最新的基因测序结果，诊断出年轻人患有一种遗传性代谢疾病。",
        "hypothesis": "年轻人患有一种遗传性代谢疾病。"
    },
    {
        "track": "pr",
        "id": 1715,
        "text": "法院还认为，尽管被告文章中“深圳送别墅”的言辞令原告产生不快可以理解，但在社会变革、价值取向多元化的今天，这一言辞在与法不悖的情况下，不会使原告应有的社会评价降低。有鉴于此，不能认定被告的行为具有贬低、损害原告名誉的性质，故原告关于被告侵犯其名誉权的主张法院不予支持。",
        "hypothesis": "被告的行为具有贬低、损害原告名誉的性质。"
    },
    {
        "track": "pr",
        "id": 1716,
        "text": "当她听到那熟悉的旋律，记起高中时期和同学们一起参加文艺汇演的情景。",
        "hypothesis": "她高中时期曾经和同学们一起参加文艺汇演。"
    },
    {
        "track": "pr",
        "id": 1717,
        "text": "差一点我就错过了这机会。真的，你不能想象这事有多么巧！",
        "hypothesis": "这事非常巧。"
    },
    {
        "track": "pr",
        "id": 1718,
        "text": "年迈的祖父坐在摇椅上，不记得昨天下午邻居家的孩子曾把一只受伤的小麻雀送给了他。",
        "hypothesis": "昨天下午邻居家的孩子没有把一只受伤的小麻雀送给他。"
    },
    {
        "track": "pr",
        "id": 1719,
        "text": "村里的老人们不知晓村口那棵看似普通的老槐树地下埋藏着千年前的瓷窑遗址。",
        "hypothesis": "村口那棵看似普通的老槐树地下没有埋藏着千年前的瓷窑遗址。"
    },
    {
        "track": "pr",
        "id": 1720,
        "text": "当我们看到人民爱八路军如子弟，八路军敬人民如父母的情感，使我们回想起过去人民对我们的疑惧，并使我们知道了唯有人民的队伍，才能与人民关系密切。",
        "hypothesis": "过去人民曾对我们有疑惧。"
    },
    {
        "track": "pr",
        "id": 1721,
        "text": "看过这次资格赛，再不能批评中国男排不拼；对比平均身高，再不能说中国男排只能以快制高。",
        "hypothesis": "中国男排很拼。"
    },
    {
        "track": "pr",
        "id": 1722,
        "text": "但当你将做笔记看成是读书的一部分，认识到做笔记的益处，便不会认为这时间白白浪费了。",
        "hypothesis": "这时间白白浪费了。"
    },
    {
        "track": "pr",
        "id": 1723,
        "text": "哨兵在浓雾弥漫的清晨警觉到远处的树林里有敌军小队正在悄悄穿越封锁线。",
        "hypothesis": "远处的树林里没有敌军小队正在悄悄穿越封锁线。"
    },
    {
        "track": "pr",
        "id": 1724,
        "text": "天文学家猜想在它的周围环绕着一颗尚未被直接拍摄到的巨大气态行星。",
        "hypothesis": "在它的周围环绕着一颗尚未被直接拍摄到的巨大气态行星。"
    },
    {
        "track": "pr",
        "id": 1725,
        "text": "那只流浪猫悄悄溜进了仓库，在堆满货物的角落里蜷缩起来，没有意识到传送带已经启动了。",
        "hypothesis": "传送带没有启动。"
    },
    {
        "track": "pr",
        "id": 1726,
        "text": "陈文婷也是被感动的观众当中的一个，不过她不愿意承认自己受了感动，就经常提醒自己道：“这是剧情的力量，不是演员的本事，也不是她编对白编得好，叫我去演，一样能动人，一样能抓住观众。”",
        "hypothesis": "陈文婷受了感动。"
    },
    {
        "track": "pr",
        "id": 1727,
        "text": "当时我们批发站库存高形竹壳水瓶六万七千多个，高形水瓶胆七千多个，矮形竹壳水瓶无货，却认为库存太大了。",
        "hypothesis": "库存不大。"
    },
    {
        "track": "pr",
        "id": 1728,
        "text": "关于苏联的对外政策趋于僵硬的原因，国际舆论认为这是典型的防御性反应。",
        "hypothesis": "这是典型的防御性反应。"
    },
    {
        "track": "pr",
        "id": 1729,
        "text": "田野考察结果证明当地特有的生态系统具备强大的自我修复能力和生物多样性维持机制。",
        "hypothesis": "当地特有的生态系统具备强大的自我修复能力和生物多样性维持机制。"
    },
    {
        "track": "pr",
        "id": 1730,
        "text": "“她浑身风湿受得很重，”大夫说。“情况很不好。”尤金很难受。他不愿意看到她受苦，但是她的病一点没有影响到他的心情",
        "hypothesis": "她没有在受苦。"
    },
    {
        "track": "pr",
        "id": 1731,
        "text": "她看到那本旧书，记起来这是她小时候父亲送给她的生日礼物。",
        "hypothesis": "那本旧书不是她小时候父亲送给她的生日礼物。"
    },
    {
        "track": "pr",
        "id": 1732,
        "text": "政府和执政党人士直截了当地指出，西欧没有单独同莫斯科谈判的基础。",
        "hypothesis": "西欧没有单独同莫斯科谈判的基础。"
    },
    {
        "track": "pr",
        "id": 1733,
        "text": "然而对于长期生活在城市的我们，现在已经无法奢望能在城市中看到这样的星空了。因为随处可见的是耀眼的路灯、灯箱广告。它们将天空遮蔽，即使在最晴朗的夏夜，我们也只能看到零星的几颗星星。",
        "hypothesis": "长期生活在城市的我们能在城市中看到这样的星空。"
    },
    {
        "track": "pr",
        "id": 1734,
        "text": "要粮要地是农民的两大要求。进一步又了解到群众怕地主。",
        "hypothesis": "群众怕地主。"
    },
    {
        "track": "pr",
        "id": 1735,
        "text": "爱弥耳活到八岁零四个月十二天就死了，我并不怀疑我的教育方法有什么重大的错误；小小的疏忽或者是免不了的，可是由大体上说，我的试验是基于十分妥当的原理上。",
        "hypothesis": "我的教育方法没有重大的错误。"
    },
    {
        "track": "pr",
        "id": 1736,
        "text": "他遗憾地指出，西方国家不愿意就裁军问题达成协议。",
        "hypothesis": "西方国家愿意就裁军问题达成协议。"
    },
    {
        "track": "pr",
        "id": 1737,
        "text": "火灾现场的指挥官眼见得火势顺着风向迅速蔓延，吞噬了相邻的木屋，浓烟滚滚直冲云霄。",
        "hypothesis": "火势没有顺着风向迅速蔓延，也没有吞噬相邻的木屋，浓烟也没有滚滚直冲云霄。"
    },
    {
        "track": "pr",
        "id": 1738,
        "text": "当我们发现手中抓到的一把米里有砂时，绝不表示米袋中混入的砂粒仅此几个。",
        "hypothesis": "米袋中混入的砂粒不止这几个。"
    },
    {
        "track": "pr",
        "id": 1739,
        "text": "清晨第一缕阳光洒进山谷时，早起的村民见到成群的候鸟正从湿地起飞向南迁徙。",
        "hypothesis": "成群的候鸟没有从湿地起飞向南迁徙。"
    },
    {
        "track": "pr",
        "id": 1740,
        "text": "她其实内心看不上他胆小怕事，只是没有表现出来。",
        "hypothesis": "他胆小怕事。"
    },
    {
        "track": "pr",
        "id": 1741,
        "text": "她结合种种迹象，推测出他此刻内心很纠结。",
        "hypothesis": "他此刻内心不纠结。"
    },
    {
        "track": "pr",
        "id": 1742,
        "text": "奥杰丽亚一出场，观众看到的完全是另外一个人了，她那富有诱惑力的表情和姿态，同第二幕中奥杰塔的温柔可爱恰恰成了鲜明的对照，使人几乎不能责怪王子会受骗。",
        "hypothesis": "王子受骗了。"
    },
    {
        "track": "pr",
        "id": 1743,
        "text": "世界各国媒体在评论日本方案时，都不约而同地指出，日本的建议带有政治动机。",
        "hypothesis": "日本的建议带有政治动机。"
    },
    {
        "track": "pr",
        "id": 1744,
        "text": "我们不准备相信金字塔就是法老们的坟墓，围绕金字塔巧合的数据太多太多，然而，这真是一种巧合吗？",
        "hypothesis": "金字塔不是法老们的坟墓。"
    },
    {
        "track": "pr",
        "id": 1745,
        "text": "敌人大举来袭之时，眼见朱家庄已烧得片瓦不存，只有向远处搜寻，决不会猜到谢逊竟是躲在火场之下。",
        "hypothesis": "谢逊躲在火场之下。"
    },
    {
        "track": "pr",
        "id": 1746,
        "text": "我从来没觉得自己比别人高明，比别人高贵，人民永远是我们的衣食父母。",
        "hypothesis": "自己比别人高明，比别人高贵。"
    },
    {
        "track": "pr",
        "id": 1747,
        "text": "在文学中，我们还经常可以见到这样一种不成文“法律”的作用，这种“法律”也不知道是谁制定的。根据它，一个因一部或几部文学著作的成功而获得名望的作家，就好像被宣告为完美无缺的了。",
        "hypothesis": "根据这种“法律”，一个因一部或几部文学著作的成功而获得名望的作家不是完美无缺的。"
    },
    {
        "track": "pr",
        "id": 1748,
        "text": "古代的居民没有认识到长期饮用含铅量过高的水源会导致神经系统受到严重损害。",
        "hypothesis": "长期饮用含铅量过高的水源会导致神经系统受到严重损害。"
    },
    {
        "track": "pr",
        "id": 1749,
        "text": "这部荒诞剧通过夸张的舞台效果讽刺现代人为了追求虚拟点赞而忽略现实亲情。",
        "hypothesis": "现代人没有为了追求虚拟点赞而忽略现实亲情。"
    },
    {
        "track": "pr",
        "id": 1750,
        "text": "当我们发现手中抓到的一把米里有砂时，绝不表示米袋中混入的砂粒仅此几个。",
        "hypothesis": "米袋中混入的砂粒仅此几个。"
    },
    {
        "track": "pr",
        "id": 1751,
        "text": "解放后，当去年该厂遣散工人时，与工人发生争执，经仲裁后，资方竟错误地认为自己胜利了，就趁机打击工会干部，企图挑拨工会与政府之间的关系。",
        "hypothesis": "资方胜利了。"
    },
    {
        "track": "pr",
        "id": 1752,
        "text": "尽量不要打搅他，他有时候也需要独处的快乐，那并不证明他不爱你。",
        "hypothesis": "他不爱你。"
    },
    {
        "track": "pr",
        "id": 1753,
        "text": "她静下心来后终于认识到自己其实一直害怕孤独。",
        "hypothesis": "她一直害怕孤独。"
    },
    {
        "track": "pr",
        "id": 1754,
        "text": "他们是在讥笑这位老农的穿着太过土气，完全配不上这样盛大的庆典场合。",
        "hypothesis": "这位老农的穿着不土气。"
    },
    {
        "track": "pr",
        "id": 1755,
        "text": "现在人们已经普遍地感觉到人口太多对社会、经济、文化教育的严重影响。",
        "hypothesis": "人口太多对社会、经济、文化教育有严重影响。"
    },
    {
        "track": "pr",
        "id": 1756,
        "text": "通观目前纯文学书籍的走势，可以说它正值上升阶段，在相当的时期内不会回落。但据此并不能断言所有的纯文学书籍都能在市场上找到出路。",
        "hypothesis": "不是所有的纯文学书籍都能在市场上找到出路。"
    },
    {
        "track": "pr",
        "id": 1757,
        "text": "她看到同事对她态度冷淡，疑心同事心里觉得她不够友好。",
        "hypothesis": "同事心里对她不够友好。"
    },
    {
        "track": "pr",
        "id": 1758,
        "text": "实现共产主义，就要有社会产品的极大丰富。绝不能设想，共产主义可以建立在落后生产力的基础上，建立在七亿农民搞饭吃的基础上。",
        "hypothesis": "共产主义可以建立在落后生产力的基础上。"
    },
    {
        "track": "pr",
        "id": 1759,
        "text": "社论认为：美帝国主义者的战争狂并不能证明他们是强有力的，相反地，证明了他们惧怕不断增长的和平力量。",
        "hypothesis": "他们不是强有力的。"
    },
    {
        "track": "pr",
        "id": 1760,
        "text": "这个时候他压倒的感情是钦佩她扔掉衣服的姿态。她用这种优雅的、毫不在乎的姿态，似乎把整个文化，整个思想制度都消灭掉了，好象老大哥、党、思想警察可以这么胳膊一挥就一扫而空似的。",
        "hypothesis": "她没有扔掉衣服。"
    },
    {
        "track": "pr",
        "id": 1761,
        "text": "这个时候他压倒的感情是钦佩她扔掉衣服的姿态。她用这种优雅的、毫不在乎的姿态，似乎把整个文化，整个思想制度都消灭掉了，好象老大哥、党、思想警察可以这么胳膊一挥就一扫而空似的。",
        "hypothesis": "她扔掉了衣服。"
    },
    {
        "track": "pr",
        "id": 1762,
        "text": "他露出一丝发自内心的微笑——真的很有意思——他突然悟到自己仍然喜欢巴纳德。",
        "hypothesis": "他仍然喜欢巴纳德。"
    },
    {
        "track": "pr",
        "id": 1763,
        "text": "科学家们推测地球的内部结构由地核、地幔和地壳组成。",
        "hypothesis": "地球的内部结构不是由地核、地幔和地壳组成。"
    },
    {
        "track": "pr",
        "id": 1764,
        "text": "指挥部在接收到前线侦察兵传回的情报后，判明敌方主力部队已经在昨夜悄然渡过了阵地前的河流。",
        "hypothesis": "敌方主力部队已经在昨夜渡过了阵地前的河流。"
    },
    {
        "track": "pr",
        "id": 1765,
        "text": "可是在这之间，鲁迅先生告诉过我，说革命文艺界中曾经有人因为他没有加入“文艺家协会”（“左联”自动解散后在一九三六年初在上海新成立的进步作家团体），就企图污蔑他是托派，而这是胡风告诉他的。",
        "hypothesis": "革命文艺界中曾经有人污蔑鲁迅是托派。"
    },
    {
        "track": "pr",
        "id": 1766,
        "text": "我敢说女工们做梦也不会想到她们的首领已经被三先生收买。",
        "hypothesis": "她们的首领已经被三先生收买。"
    },
    {
        "track": "pr",
        "id": 1767,
        "text": "仅凭简单的几张存取款凭证，证明不了李百锁存了6万多元，也证明不了是柜员拿走了那2万多元。",
        "hypothesis": "李百锁没有存6万多元。"
    },
    {
        "track": "pr",
        "id": 1768,
        "text": "谈判专家没准备直接同意绑匪提出的苛刻要求。",
        "hypothesis": "谈判专家将直接同意绑匪提出的苛刻要求。"
    },
    {
        "track": "pr",
        "id": 1769,
        "text": "因此，西方三国代表团关于德国问题新建议的出现，并不是偶然的。这些建议不但没有暗示美、英、法三国政府迄今对德国所奉行的政策是正确的，而且相反，却直率说出有必要加紧势力，恢复德国经济与政治的统一，以便在下届外长会议上获致最近一届会议在这方面所未能达成的结果。",
        "hypothesis": "美、英、法三国政府迄今对德国所奉行的政策是正确的。"
    },
    {
        "track": "pr",
        "id": 1770,
        "text": "母亲怪怨邻居家的孩子打碎了窗户的玻璃。",
        "hypothesis": "邻居家的孩子打碎了窗户的玻璃。"
    },
    {
        "track": "pr",
        "id": 1771,
        "text": "学生们静坐在行政楼前，抗议学校管理层将住宿费用提高了百分之三十。",
        "hypothesis": "学校管理层没有提高住宿费用。"
    },
    {
        "track": "pr",
        "id": 1772,
        "text": "这个伙计并不晓得掌柜的安着一肚子坏杂碎，想着这些事也在情理之中。",
        "hypothesis": "掌柜的没有安着一肚子坏杂碎。"
    },
    {
        "track": "pr",
        "id": 1773,
        "text": "我真的很难忘记馒头店店主哭泣的画面。",
        "hypothesis": "馒头店店主曾经在哭泣。"
    },
    {
        "track": "pr",
        "id": 1774,
        "text": "伊拉克驻联合国大使安巴里在发言中谴责了美国空袭巴格达造成几百名平民死亡的“战争罪行”，但据外交人士说，安巴里在发言中没有暗示伊拉克准备撤出科威特。",
        "hypothesis": "伊拉克准备撤出科威特。"
    },
    {
        "track": "pr",
        "id": 1775,
        "text": "可是，人们并没有听说不去白山水电站报到的毕业生被取消了分配资格。",
        "hypothesis": "不去白山水电站报到的毕业生被取消了分配资格。"
    },
    {
        "track": "pr",
        "id": 1776,
        "text": "即使是最坚定的支持者，在看到最新的调查报告后也不否认该项目的实施对当地生态环境造成了不可逆转的影响。",
        "hypothesis": "该项目的实施对当地生态环境造成了不可逆转的影响。"
    }
]